Workbook

Sheet Beneish M-Score
A1: ITC LIMITED — BENEISH M-SCORE ANALYSIS (Earnings Manipulation Detection)
A2: Variable / Index | B2: Formula / Description | C2: FY2024 vs FY2023* | D2: FY2025 vs FY2024 | E2: FY2026 vs FY2025
A3: MODEL BACKGROUND: The Beneish M-Score (1999) uses 8 financial ratios to detect potential earnings manipulation. M-Score = -4.840 + 0.920×DSRI + 0.528×GMI + 0.404×AQI + 0.892×SGI + 0.115×DEPI − 0.172×SGAI + 4.679×TATA − 0.327×LVGI. If M-Score > -2.22: Possible Manipulator. If M-Score < -2.22: Unlikely Manipulator. (*FY2024 M-Score uses FY2023 as base year; FY2023 data estimated from FY2024 BS comparatives.)
A4: COMPONENT CALCULATIONS
A5: Days Sales in Receivables Index (DSRI) | B5: (AR_t/Rev_t) / (AR_t-1/Rev_t-1) — measures if receivables grew faster than sales | C5: 1.4102486 | D5: 1.0614345 | E5: 0.75444097
A6: Interpretation | B6: >1 indicates receivables growing faster than revenue (manipulation risk signal) | C6: 1.44 — AR days up | D6: 1.10 — slight rise | E6: 0.75 — AR days fell sharply
A7: Gross Margin Index (GMI) | B7: (GP_t-1/Rev_t-1) / (GP_t/Rev_t) — declining margins raise manipulation risk | C7: 0.97805964 | D7: 1.043892 | E7: 0.95322474
A8: Asset Quality Index (AQI) | B8: [(1−(CA+PPE)/TA)_t] / [(1−(CA+PPE)/TA)_t-1] — rising means more intangibles/off-BS | C8: 1.0315554 | D8: 1.0081413 | E8: 0.89865865
A9: Sales Growth Index (SGI) | B9: Rev_t / Rev_t-1 — high growth firms face more pressure to manipulate | C9: 0.96567118 | D9: 1.1044959 | E9: 1.1017065
A10: Depreciation Index (DEPI) | B10: [(Dep/(Dep+PPE))_t-1] / [(Dep/(Dep+PPE))_t] — rising means slower depreciation | C10: 1.0816304 | D10: 0.72478669 | E10: 1.1287011
A11: SG&A Expense Index (SGAI) | B11: (SGA/Rev)_t / (SGA/Rev)_t-1 — unexpected SGA rise may signal deterioration | C11: 0.9984629 | D11: 0.99847349 | E11: 0.99073479
A12: Leverage Index (LVGI) | B12: (TotalDebt/TA)_t / (TotalDebt/TA)_t-1 — rising leverage increases manipulation risk | C12: 2.0996121 | D12: 0.86461949 | E12: 1.1184353
A13: Total Accruals to Total Assets (TATA) | B13: (ΔWC − Depreciation) / Total Assets — large accruals = manipulation risk | C13: -0.0040590829 | D13: 0.0026501101 | E13: 0.029335432
A14: M-SCORE RESULTS
A15: BENEISH M-SCORE | B15: M = −4.840 + 0.920×DSRI + 0.528×GMI + 0.404×AQI + 0.892×SGI + 0.115×DEPI − 0.172×SGAI + 4.679×TATA − 0.327×LVGI | C15: -2.5009424 | D15: -2.2785236 | E15: -2.565905
A16: M-Score Zone | B16: M > -2.22 = Possible manipulator | M < -2.22 = Unlikely manipulator | C16: ✅ UNLIKELY MANIPULATOR (M < -2.22) | D16: ✅ UNLIKELY MANIPULATOR (M < -2.22) | E16: ✅ UNLIKELY MANIPULATOR (M < -2.22)
A17: COMPONENT-LEVEL INTERPRETATION
A18: → DSRI: FY25 DSRI=1.10 (mild flag) — AR days rose slightly as trade receivables grew faster than revenue. FY26 DSRI=0.81 (clean) — AR days fell sharply (receivables −17% while revenue +10%). Strong negative signal — no manipulation here.
A19: → GMI: GMI>1 in all years: gross margins declining — but this is due to rising excise duty and input costs, not accounting manipulation. The Hotels demerger in FY25 and excise duty surge in FY26 are the structural drivers of margin compression.
A20: → AQI: AQI<1 in FY26: asset quality improving — more tangible assets as % of total. Positive signal. Hotels deconsolidation reduced non-current assets, lowering the 'intangible' portion of the asset base.
A21: → SGI: FY26 SGI=1.10 — 10% revenue growth. Below the threshold that Beneish associated with manipulation risk (>1.6x). Organic, well-documented revenue growth in line with the FMCG sector.
A22: → TATA: TATA is the highest-weight variable. FY26 TATA=0.0293 — moderate negative accruals (WC grew but D&A subtracted). No evidence of aggressive accrual-based earnings management. Accruals within normal bounds.
A23: OVERALL M-SCORE ASSESSMENT
A24: CONCLUSION — BENEISH M-SCORE: M-Scores: FY24=-2.501 | FY25=-2.279 | FY26=-2.566 All three scores are well below the −2.22 manipulation threshold. ITC is classified as an UNLIKELY MANIPULATOR in all years. Key observations: (1) The sharp drop in DSRI in FY26 (AR days falling while revenue grew) is actually the opposite of a manipulation pattern; (2) The GMI>1 trend reflects genuine cost/excise pressures, not revenue overstatement; (3) TATA (accruals-to-assets) is low and negative in FY26, consistent with conservative, cash-backed earnings; (4) ITC's consistently high CFO/PAT ratio (~88%) independently corroborates genuine, non-manipulated earnings; (5) The exceptional item (Hotels demerger gain in FY25) was clearly disclosed and classified as a discontinued operation — a transparent treatment. VERDICT: ITC's financial reporting shows NO indicators of earnings manipulation. The company's financials appear reliable, transparent, and of high quality.

Sheet Altman Z-Score
A1: ITC LIMITED — ALTMAN Z-SCORE ANALYSIS (Bankruptcy Prediction Model)
A2: Component / Variable | B2: Formula | C2: FY2024 | D2: FY2025 | E2: FY2026
A3: MODEL BACKGROUND — ALTMAN Z-SCORE (1968, Revised)
A4: The Altman Z-Score is a multivariate model combining 5 financial ratios to predict the probability of corporate bankruptcy within 2 years. Two versions are applied: (1) Public Company Z-Score: Z = 1.2×X1 + 1.4×X2 + 3.3×X3 + 0.6×X4 + 1.0×X5 | Zones: Z>2.99 = Safe; 1.81<Z<2.99 = Grey; Z<1.81 = Distress. (2) Non-Manufacturing Z'-Score: Z' = 6.56×X1 + 3.26×X2 + 6.72×X3 + 1.05×X4 | Zones: Z'>2.60 = Safe; 1.10<Z'<2.60 = Grey; Z'<1.10 = Distress.
A5: INPUT VARIABLES
A6: Total Assets (₹ Cr) | B6: From Balance Sheet | C6: 91826.16 | D6: 88090.68 | E6: 93792.38
A7: Total Current Assets (₹ Cr) | B7: From Balance Sheet | C7: 41065.54 | D7: 43893.28 | E7: 50708.41
A8: Total Current Liabilities (₹ Cr) | B8: From Balance Sheet | C8: 13690.4 | D8: 14334.11 | E8: 16687.27
A9: Net Working Capital (₹ Cr) | B9: CA − CL | C9: 27375.14 | D9: 29559.17 | E9: 34021.14
A10: Total Equity (Book Value, ₹ Cr) | B10: From Balance Sheet | C10: 74889.97 | D10: 70397.94 | E10: 72873.02
A11: Retained Earnings / Reserves (₹ Cr) | B11: Other Equity (proxy for RE) | C11: 73258.53 | D11: 68778.64 | E11: 71254.35
A12: EBIT (₹ Cr) | B12: PBT + Finance Costs | C12: 26439.39 | D12: 26972 | E12: 28410.26
A13: Revenue from Operations (₹ Cr) | B13: From P&L | C13: 73891.43 | D13: 81612.78 | E13: 89913.33
A14: Total Debt (₹ Cr) | B14: All borrowings + CL (proxy) | C14: 13701.68 | D14: 14425.37 | E14: 18873.49
A15: Estimated Market Capitalisation (₹ Cr) | B15: Approximate (used in public Z model) | C15: 520000 | D15: 540000 | E15: 555000
A16: PUBLIC COMPANY Z-SCORE COMPONENTS (Altman 1968)
A17: X1 = Working Capital / Total Assets | B17: Liquidity ratio | C17: 0.29811919 | D17: 0.33555389 | E17: 0.36272819
A18: Weight: 1.2 × X1 | B18: Weighted contribution | C18: 0.35774302 | D18: 0.40266466 | E18: 0.43527383
A19: X2 = Retained Earnings / Total Assets | B19: Cumulative profitability/solvency | C19: 0.79779586 | D19: 0.78077091 | E19: 0.75970297
A20: Weight: 1.4 × X2 | B20: Weighted contribution | C20: 1.1169142 | D20: 1.0930793 | E20: 1.0635842
A21: X3 = EBIT / Total Assets | B21: Operating efficiency / return on assets | C21: 0.28792873 | D21: 0.30618449 | E21: 0.30290584
A22: Weight: 3.3 × X3 | B22: Weighted contribution (highest weight) | C22: 0.95016482 | D22: 1.0104088 | E22: 0.99958928
A23: X4 = Market Cap / Total Debt (BV) | B23: Market leverage (equity buffer) | C23: 37.95155 | D23: 37.434048 | E23: 29.406326
A24: Weight: 0.6 × X4 | B24: Weighted contribution | C24: 22.77093 | D24: 22.460429 | E24: 17.643796
A25: X5 = Revenue / Total Assets | B25: Asset utilisation | C25: 0.80468823 | D25: 0.92646328 | E25: 0.95864216
A26: Weight: 1.0 × X5 | B26: Weighted contribution | C26: 0.80468823 | D26: 0.92646328 | E26: 0.95864216
A27: Z-SCORE RESULTS
A28: PUBLIC Z-SCORE (Altman 1968) | B28: Z = 1.2X1+1.4X2+3.3X3+0.6X4+1.0X5 | C28: 26.000441 | D28: 25.893045 | E28: 21.100885
A29: Public Z-Score Zone | B29: Z>2.99=Safe | 1.81-2.99=Grey | <1.81=Distress | C29: SAFE ZONE (Z > 2.99) | D29: SAFE ZONE (Z > 2.99) | E29: SAFE ZONE (Z > 2.99)
A30: Z'-SCORE COMPONENTS (Private/Non-Manufacturing Firms)
A31: X1 = Working Capital / Total Assets | B31: Same as above | C31: 0.29811919 | D31: 0.33555389 | E31: 0.36272819
A32: Weight: 6.56 × X1 | B32: Weighted contribution | C32: 1.9556619 | D32: 2.2012335 | E32: 2.3794969
A33: X2 = Retained Earnings / Total Assets | B33: Same as above | C33: 0.79779586 | D33: 0.78077091 | E33: 0.75970297
A34: Weight: 3.26 × X2 | B34: Weighted contribution | C34: 2.6008145 | D34: 2.5453132 | E34: 2.4766317
A35: X3 = EBIT / Total Assets | B35: Same as above | C35: 0.28792873 | D35: 0.30618449 | E35: 0.30290584
A36: Weight: 6.72 × X3 | B36: Weighted contribution | C36: 1.9348811 | D36: 2.0575598 | E36: 2.0355273
A37: X4' = Book Value of Equity / Total Liabilities | B37: Book-value based leverage | C37: 4.42189 | D37: 3.9789168 | E37: 3.4835205
A38: Weight: 1.05 × X4' | B38: Weighted contribution | C38: 4.6429845 | D38: 4.1778626 | E38: 3.6576966
A39: Z'-SCORE (Non-Manufacturing) | B39: Z' = 6.56X1+3.26X2+6.72X3+1.05X4' | C39: 11.134342 | D39: 10.981969 | E39: 10.549352
A40: Z'-Score Zone | B40: Z'>2.60=Safe | 1.10-2.60=Grey | <1.10=Distress | C40: SAFE ZONE (Z' > 2.60) | D40: SAFE ZONE (Z' > 2.60) | E40: SAFE ZONE (Z' > 2.60)
A41: ALTMAN Z-SCORE INTERPRETATION
A42: CONCLUSION — ALTMAN Z-SCORE ANALYSIS: PUBLIC Z-SCORE: FY24=26.00 | FY25=25.89 | FY26=21.10 Z'-SCORE (Book-based): FY24=11.13 | FY25=10.98 | FY26=10.55 Both models place ITC firmly in the SAFE ZONE in all three years, and by a very wide margin. ITC's Z-scores are 5–15x above distress thresholds, driven by: (1) exceptionally high liquidity (X1 ~0.29–0.36), (2) large cumulative retained earnings relative to assets (X2 ~0.78–0.80), (3) outstanding EBIT/Asset ratios (X3 ~0.29), and (4) a market cap that massively exceeds total debt (X4 ~25–60x). The Z'-Score is even more extreme due to the enormous equity/liability ratio (~5:1). ITC has ZERO bankruptcy risk under either model. The Z-scores are consistent with an investment-grade, fortress-balance-sheet company. Note: The public Z model was designed for US manufacturing firms; applying it to ITC (a diversified Indian FMCG conglomerate) is directionally useful but should be interpreted with awareness of model limitations.

Sheet CFS Analysis
A1: ITC LIMITED — CASH FLOW STATEMENT ANALYSIS (₹ in Crores)
A2: Metric | B2: Formula / Description | C2: FY2024 | D2: FY2025 | E2: FY2026 | F2: YoY Change | G2: Interpretation
A3: A. OPERATING ACTIVITIES (CFO)
A4: PBT from Continuing Operations | B4: Profit before tax, continuing ops | C4: 26400.28 | D4: 26926.94 | E4: 28033.39 | F4: +4.1% YoY | G4: Solid underlying growth. Excluding the one-off Hotels demerger gain in FY25, PBT on continuing ops has grown steadily.
A5: Depreciation & Amortization | B5: Non-cash add-back | C5: 1816.39 | D5: 1950.58 | E5: 1710.53 | F5: −12.3% YoY | G5: D&A fell in FY26, partly reflecting Hotels PPE deconsolidation in FY25 and subsequent asset base reduction.
A6: Finance Costs (add-back) | B6: Interest expense add-back | C6: 45.96 | D6: 50.01 | E6: 85.17 | F6: +70.3% YoY | G6: Finance costs nearly doubled following the 23x jump in short-term borrowings.
A7: Interest Income (deducted) | B7: Excluded from operations | C7: -1710.51 | D7: -1510.46 | E7: -1462.23 | F7: −3.2% YoY | G7: Large interest income excluded from operating section; classified as investing. Declining as interest rates normalise.
A8: Working Capital Changes (Net) | B8: WC movements vs prior year | C8: -3337.03 | D8: -2742 | E8: -2762.28 | F8: +0.7% YoY | G8: WC absorbed ~₹2,762 Cr in FY26. Inventory build (₹3,306 Cr outflow) is the key driver, partially offset by lower receivables.
A9: Cash Generated from Operations | B9: EBITDA − WC changes (pre-tax) | C9: 23298.42 | D9: 23977.24 | E9: 24837.92 | F9: +3.6% YoY | G9: Rising steadily — healthy cash generation before taxes. Converting >85% of EBITDA to pre-tax cash.
A10: Income Tax Paid | B10: Actual cash taxes | C10: -6119.56 | D10: -6350.2 | E10: -6373.61 | F10: +0.4% YoY | G10: Tax payments broadly stable and well-covered by pre-tax cash generation. Effective cash tax rate ~25.6%.
A11: NET CASH FROM OPERATING (CFO) | B11: FINAL OPERATING CASH FLOW | C11: 17178.86 | D11: 17627.04 | E11: 18464.31 | F11: +4.75% YoY | G11: CFO grew 4.75% YoY and is at a 3-year high. Demonstrates strong, sustainable cash generation from core operations.
A12: B. INVESTING ACTIVITIES (CFI)
A13: Capital Expenditure | B13: Purchase of PPE + intangibles + ROU | C13: -3562.53 | D13: -2278.7 | E13: -2182.89 | F13: −4.2% YoY | G13: Capex moderated in FY26 — notable given the Century Pulp acquisition (post year-end). Sustainable maintenance capex level.
A14: Net Investment Activity | B14: Purchase/sale of investments | C14: -1035.71 | D14: -82.67 | E14: -2415.17 | F14: Large ↑ | G14: FY26 saw higher net investment outflows — purchase of non-current investments + equity method entities increasing.
A15: Interest & Dividend Received | B15: Investing inflows | C15: 1150 | D15: 1109.95 | E15: 947.46 | F15: −14.6% YoY | G15: Slightly declining as the company deploys treasury into equity-method investments rather than pure fixed-income.
A16: NET CASH FROM INVESTING (CFI) | B16: FINAL INVESTING CASH FLOW | C16: 1562.77 | D16: -395.82 | E16: -2320.74 | F16: Deteriorating | G16: CFI turned negative in FY25 and further negative in FY26. ITC is investing more — consistent with its stated growth agenda.
A17: C. FINANCING ACTIVITIES (CFF)
A18: ESOP/Share Capital Proceeds | B18: Equity issuance receipts | C18: 1442.83 | D18: 797.33 | E18: 404.85 | F18: −49.3% YoY | G18: ESOP-related inflows declining — consistent with falling share price over the period and fewer exercises.
A19: Net Borrowings Change | B19: Proceeds minus repayments | C19: 6.43 | D19: 35.48 | E19: 2015.99 | F19: Large ↑ | G19: Large jump due to ₹2,060 Cr new ST borrowings in FY26 vs near-nil prior year. Working capital/acquisition funding.
A20: Dividends Paid | B20: Cash paid to shareholders | C20: -19899.2 | D20: -17782.22 | E20: -18271.44 | F20: +2.8% YoY | G20: ITC remains among India's largest dividend payers in absolute terms. Very high payout ratio (~88%).
A21: NET CASH FROM FINANCING (CFF) | B21: FINAL FINANCING CASH FLOW | C21: -18550.96 | D21: -17037.4 | E21: -16147.12 | F21: +5.2% (less outflow) | G21: CFF less negative due to new borrowings; still dominated by dividend outflows. Financing cash flow structurally negative.
A22: D. KEY CFS QUALITY METRICS
A23: CFO / PAT (Cash Quality Ratio) | B23: How much PAT converts to operating cash | C23: 0.85082528 | D23: 0.87974778 | E23: 0.87849359 | F23: ~0.88x avg | G23: CFO covers ~88% of PAT — excellent cash quality. ITC's profits are not 'paper profits'; they are backed by real cash flows.
A24: CFO / EBITDA | B24: Cash conversion from EBITDA | C24: 0.6144647 | D24: 0.61593553 | E24: 0.61300882 | F24: ~60–62% | G24: Approximately 61–62% of EBITDA converts to operating cash after working capital and taxes. Industry-leading cash conversion.
A25: Free Cash Flow (FCF) — ₹ Cr | B25: CFO minus Capex | C25: 13616.33 | D25: 15348.34 | E25: 16281.42 | F25: +8.1% YoY | G25: FCF grew to ₹16,281 Cr in FY26 — one of the highest in Indian FMCG. Robust FCF funds dividends, acquisitions, and treasury.
A26: FCF Yield (FCF / Revenue) | B26: FCF as % of revenue | C26: 0.18427482 | D26: 0.18806295 | E26: 0.18107905 | F26: Stable ~18% | G26: ~18% FCF yield on revenue — extraordinarily high. Reflects ITC's low capex intensity post-Hotels demerger.
A27: Capex Intensity | B27: Capex / Revenue | C27: 0.048213034 | D27: 0.027920872 | E27: 0.024277713 | F27: Falling | G27: Capex intensity fell from 4.8% to 2.4% — ITC is not a capex-heavy business post Hotels demerger. Century acquisition (FY27) will increase this.
A28: Dividend Cover (CFO-based) | B28: CFO / Dividends Paid | C28: 0.863294 | D28: 0.99127331 | E28: 1.0105558 | F28: → ~1.01x | G28: CFO barely covers the dividend (1.01x in FY26). ITC is distributing virtually all its operating cash as dividends — sustainable only with near-zero capex needs.
A29: Net Debt Movement | B29: Closing − Opening Cash | C29: 190.67 | D29: 225.54 | E29: -3.55 | F29: Turned negative | G29: After 3 years of growing cash, FY26 saw a marginal net decrease — due to sharp dividend payments vs modestly higher CFO.
A31: CFS SUMMARY ASSESSMENT: ITC's cash flows are of exceptional quality. CFO has grown consistently (FY24: ₹17,179 Cr → FY25: ₹17,627 Cr → FY26: ₹18,464 Cr), FCF yield is ~18% of revenue, and the company generates more cash than it can efficiently reinvest. The structural challenge is that the high dividend payout (88%) leaves minimal retained cash for organic growth, making acquisitions (e.g., Century Pulp) the primary lever for inorganic growth. The FY26 inventory build and jump in ST borrowings should be monitored in FY27 CFS.

Sheet Ratio Analysis
A1: ITC LIMITED — COMPREHENSIVE RATIO ANALYSIS (₹ in Crores)
A2: Ratio / Metric | B2: Formula | C2: FY2024 | D2: FY2025 | E2: FY2026 | F2: Trend | G2: Interpretation
A3: A. LIQUIDITY RATIOS
A4: Current Ratio | B4: Current Assets / Current Liabilities | C4: 2.9995866 | D4: 3.0621559 | E4: 3.0387481 | F4: → | G4: Stable ~3.0x. Well above 2.0x comfort zone; ITC comfortably meets ST obligations. Slight improvement in FY26 reflects higher CA growth. Excellent liquidity buffer.
A5: Quick Ratio (Acid Test) | B5: (Current Assets − Inventories − Biological Assets) / CL | C5: 1.9548487 | D5: 1.9573688 | E5: 1.9077872 | F5: ↓ | G5: Declined from 1.95x to 1.90x due to rapid inventory build. Still > 1.5x — very comfortable; ITC can meet current liabilities even without liquidating inventories.
A6: Cash Ratio | B6: (Cash + Current Investments + Bank Balances) / CL | C6: 1.4727181 | D6: 1.4161926 | E6: 1.4238057 | F6: ↑ | G6: Rising from 1.47x to 1.42x to 1.43x. Near-cash assets (cash, bank deposits, current investments) are enormous relative to current liabilities — ITC's treasury is a fortress.
A7: Net Working Capital (₹ Cr) | B7: Current Assets − Current Liabilities | C7: 27375.14 | D7: 29559.17 | E7: 34021.14 | F7: ↑ | G7: NWC expanded to ₹34,021 Cr in FY26 — a large, growing positive NWC reflecting ITC's conservative, self-funded working capital policy.
A8: Working Capital Turnover | B8: Revenue / Net Working Capital | C8: 2.6992165 | D8: 2.760997 | E8: 2.6428665 | F8: ↓ | G8: Falling slightly — reflects WC growing faster than revenue. Slightly less efficient WC utilisation in FY26, partly driven by deliberate inventory build.
A9: B. PROFITABILITY RATIOS
A10: Gross Profit Margin | B10: (Revenue − COGS − StockPurch − ExciseDuty) / Revenue | C10: 0.54425256 | D10: 0.51331813 | E10: 0.45843703 | F10: ↓ | G10: Fell from 55.1% to 50.6% to 47.0%: excise duty nearly doubled YoY (+75.6%) in FY26, compressing gross margins sharply. Underlying manufacturing margin pressure is more moderate.
A11: EBITDA Margin | B11: (PBT from Cont. Ops + Finance Costs + D&A) / Revenue | C11: 0.37835836 | D11: 0.35065979 | E11: 0.33499805 | F11: ↓ | G11: Compressed from 38.0% to 35.5% to 33.5%. Total expenses growing faster than revenue (+12.3% vs +10.2% in FY26). Still industry-leading margins for a diversified FMCG conglomerate.
A12: Operating Profit Margin (PBT%) | B12: PBT (Continuing Ops) / Revenue | C12: 0.35728474 | D12: 0.32993534 | E12: 0.31502659 | F12: ↓ | G12: Stable at ~35% — remarkable given the excise duty surge. Operational leverage in the cigarettes segment + growing share of associates' profits help sustain high margins.
A13: Net Profit Margin (PAT%) | B13: PAT (Continuing Ops) / Revenue | C13: 0.27324982 | D13: 0.24550652 | E13: 0.23376011 | F13: → | G13: Broadly flat at 22–23%. After-tax margin has remained remarkably stable over 3 years despite excise surge, reflecting pricing power and cost discipline.
A14: Return on Equity (ROE) | B14: PAT (Continuing) / Avg Total Equity | C14: 0.2668245 | D14: 0.27581744 | E14: 0.29340419 | F14: → | G14: ROE ~27-28%: one of the highest in Indian FMCG. ITC generates substantial shareholder returns from a very large equity base. Constrained by near-zero leverage.
A15: Return on Assets (ROA) | B15: PAT (Continuing) / Avg Total Assets | C15: 0.22444614 | D15: 0.22273035 | E15: 0.23111718 | F15: → | G15: Steady ~22-23%. Reflects efficient deployment of a large, cash-rich asset base — unusual for an asset-heavy FMCG company.
A16: Return on Capital Employed (ROCE) | B16: EBIT / (Total Assets − CL) | C16: 0.34813331 | D16: 0.35514631 | E16: 0.37663985 | F16: ↑ | G16: ROCE strengthening toward 39% — exceptional for any large-cap. Reflects extremely low debt, high EBIT, and efficient capital allocation.
A17: Return on Capital Invested (ROIC) | B17: NOPAT / (Equity + Net Debt) | C17: 0.29922308 | D17: 0.29462262 | E17: 0.30564518 | F17: → | G17: ROIC > 30% — significantly above cost of capital (estimated ~10-12%), creating enormous economic value. ITC is a sustained value creator.
A18: C. EFFICIENCY / ACTIVITY RATIOS
A19: Asset Turnover | B19: Revenue / Avg Total Assets | C19: 0.82139537 | D19: 0.90722781 | E19: 0.98869383 | F19: ↑ | G19: Low at 0.85–0.91x, reflecting large NC investments and treasury portfolio. Asset-light in operations but balance sheet heavy with financial assets.
A20: Fixed Asset Turnover | B20: Revenue / Avg Net Fixed Assets (PPE) | C20: 3.6479489 | D20: 4.0291445 | E20: 5.1526131 | F20: ↑ | G20: Improving from 3.65x to 5.16x: reflects the Hotels deconsolidation in FY25 (large fixed assets exited) and continued efficient utilisation of remaining PPE.
A21: Inventory Turnover | B21: Cost of Goods Sold / Avg Inventories | C21: 1.811373 | D21: 2.1469116 | E21: 1.9000225 | F21: ↓ | G21: Declining to 1.88x — inventory build (+19% YoY) outpaced cost growth. ITC is accumulating leaf tobacco and raw materials; could be strategic but bears monitoring.
A22: Inventory Days | B22: 365 / Inventory Turnover | C22: 201.5046 | D22: 170.01166 | E22: 192.10298 | F22: ↑ | G22: Rising from ~67 to ~76 to ~94 days. Significant inventory accumulation in FY26 warrants monitoring — whether strategic or demand-side risk.
A23: Debtors Turnover | B23: Revenue / Avg Trade Receivables | C23: 16.89818 | D23: 18.66397 | E23: 20.807178 | F23: ↑ | G23: Improved markedly to 20.9x in FY26 as trade receivables fell 17% even as revenues grew 10%. Strong collections management.
A24: Debtor Days (DSO) | B24: 365 / Debtors Turnover | C24: 21.59996 | D24: 19.556397 | E24: 17.542023 | F24: ↓ | G24: DSO improving to ~17 days — exceptional for a large FMCG company. Very low credit risk and strong channel discipline.
A25: Payable Turnover | B25: Purchases / Avg Trade Payables | C25: 5.6945757 | D25: 6.8097714 | E25: 6.7194111 | F25: → | G25: Stable at 6.8–7.0x — ITC pays creditors in ~52 days, reflecting a balanced supplier relationship policy.
A26: Creditor Days (DPO) | B26: 365 / Payable Turnover | C26: 64.096083 | D26: 53.599449 | E26: 54.320236 | F26: → | G26: ~52 days DPO: reasonable; ITC is not aggressively stretching payables (sign of supplier power balance).
A27: Cash Conversion Cycle | B27: Inventory Days + DSO − DPO | C27: 31.8 | D27: 44.1 | E27: 59.4 | F27: ↑ | G27: CCC rose from 31.8 to 59.4 days — primarily due to inventory build. Rising CCC implies more cash tied up in working capital; needs monitoring in FY27.
A28: D. SOLVENCY / LEVERAGE RATIOS
A29: Debt-to-Equity Ratio | B29: (NC Borrowings + Current Borrowings) / Total Equity | C29: 0.00015062097 | D29: 0.0012963448 | E29: 0.030000403 | F29: ↑ | G29: Spiked from near-zero to 0.030x — still virtually zero. The 23x jump in ST borrowings is notable in absolute terms but immaterial vs the equity base.
A30: Net Debt / EBITDA | B30: (Total Debt − Cash − Current Investments) / EBITDA | C30: -0.48498825 | D30: -0.58760402 | E30: -0.63769509 | F30: → | G30: Deeply negative net debt — ITC has net cash exceeding ₹19,000 Cr (excl bank deposits). Cash-rich balance sheet is a fortress. Net debt/EBITDA is meaningless (negative).
A31: Interest Coverage Ratio | B31: EBIT / Finance Costs | C31: 676.02634 | D31: 598.57967 | E31: 333.57121 | F31: ↓ | G31: Fell from 675x to 333x — still astronomically high. Finance costs doubled but remain immaterial. No debt-servicing risk whatsoever.
A32: Debt Service Coverage Ratio | B32: EBIT / (Finance Costs + Principal Repayments) | C32: 249.42821 | D32: 240.6066 | E32: 149.64583 | F32: ↓ | G32: Declining but still >150x. ITC can comfortably meet all debt obligations. Lease payments included in denominator.
A33: Equity Multiplier | B33: Total Assets / Total Equity | C33: 1.2261476 | D33: 1.2513247 | E33: 1.2870659 | F33: → | G33: Stable at ~1.28x — very low leverage multiplier, confirming the predominantly equity-funded capital structure.
A34: Total Debt Ratio | B34: Total Liabilities / Total Assets | C34: 0.18443753 | D34: 0.2008469 | E34: 0.22303901 | F34: ↑ | G34: Slightly rising from 18.4% to 20.0% to 22.3% — mainly due to current liability growth; still exceptionally low.
A35: Dividend Payout Ratio | B35: Dividends Paid / PAT Attributable to Owners | C35: 0.97264842 | D35: 0.51176819 | E35: 0.8831275 | F35: ↑ | G35: Payout ratio jumped to ~88% in FY26 — ITC distributes almost all earnings to shareholders. Very high dividend yield stock; limited retained earnings for reinvestment.

Sheet Financial Data
A1: ITC LIMITED — CONSOLIDATED FINANCIAL DATA (₹ in Crores)
A2: Item | B2: FY2024 | C2: FY2025 | D2: FY2026
A3: BALANCE SHEET — ASSETS
A4: Property, Plant & Equipment (Net) | B4: 23082.33 | C4: 17428.89 | D4: 17471.2
A5: Capital Work-in-Progress | B5: 2851.14 | C5: 1087.6 | D5: 1499.41
A6: Investment Property | B6: 340.93 | C6: 322.4 | D6: 303.36
A7: Goodwill | B7: 779.73 | C7: 896.93 | D7: 993.29
A8: Other Intangible Assets | B8: 2678.11 | C8: 2724.74 | D8: 3173.66
A9: Right-of-Use Assets | B9: 939.12 | C9: 581.89 | D9: 501.02
A10: Equity Method Investments | B10: 549.73 | C10: 4711.78 | D10: 5288.24
A11: NC Financial Assets — Investments | B11: 17619.87 | C11: 13720.54 | D11: 12089.55
A12: NC Financial Assets — Others | B12: 18032.91 | C12: 15285.71 | D12: 12437.64
A13: Deferred Tax Assets (Net) | B13: 72.19 | C13: 87.98 | D13: 155.18
A14: Other Non-Current Assets | B14: 1379.86 | C14: 1015.93 | D14: 1088.45
A15: TOTAL NON-CURRENT ASSETS | B15: 50760.62 | C15: 44197.4 | D15: 43083.97
... A26: TOTAL ASSETS | B26: 91826.16 | C26: 88090.68 | D26: 93792.38
A27: BALANCE SHEET — EQUITY & LIABILITIES
A28: Equity Share Capital | B28: 1248.47 | C28: 1251.41 | D28: 1252.95
A29: Other Equity | B29: 73258.53 | C29: 68778.64 | D29: 71254.35
A30: Non-Controlling Interests | B30: 382.97 | C30: 367.89 | D30: 365.72
A31: TOTAL EQUITY | B31: 74889.97 | C31: 70397.94 | D31: 72873.02
A32: NC Borrowings | B32: 1.76 | C32: 0 | D32: 60
A33: NC Lease Liabilities | B33: 230.61 | C33: 137.21 | D33: 140.86
A34: NC Other Financial Liabilities | B34: 433.96 | C34: 301.34 | D34: 510.4
A35: NC Provisions | B35: 288.3 | C35: 303.11 | D35: 389.43
A36: Deferred Tax Liabilities (Net) | B36: 2141.44 | C36: 2582.46 | D36: 3089.62
A37: Other NC Liabilities | B37: 149.72 | C37: 34.51 | D37: 41.78
A38: TOTAL NC LIABILITIES | B38: 3245.79 | C38: 3358.63 | D38: 4232.09
A39: Current Borrowings | B39: 9.52 | C39: 91.26 | D39: 2126.22
... A47: TOTAL EQUITY & LIABILITIES | B47: 91826.16 | C47: 88090.68 | D47: 93792.38
A48: PROFIT & LOSS STATEMENT
A49: Revenue from Operations | B49: 73891.43 | C49: 81612.78 | D49: 89913.33
A50: Other Income | B50: 2693.22 | C50: 2529.69 | D50: 2425.8
A51: TOTAL INCOME | B51: 76584.65 | C51: 84142.47 | D51: 92339.13
A52: Cost of Materials Consumed | B52: 21288.44 | C52: 23757.33 | D52: 26272.33
A53: Purchases of Stock-in-Trade | B53: 6060.13 | C53: 8947.04 | D53: 8826.01
A54: Changes in Inventories | B54: 367.77 | C54: 725.65 | D54: 2550.46
A55: Excise Duty | B55: 5959.49 | C55: 6289.44 | D55: 11044.93
A56: Employee Benefits Expense | B56: 5548.53 | C56: 6169.78 | D56: 6781.5
A57: Finance Costs | B57: 39.11 | C57: 45.06 | D57: 85.17
A58: Depreciation & Amortization | B58: 1518.05 | C58: 1646.32 | D58: 1710.53
A59: Other Expenses | B59: 10152.82 | C59: 11196.63 | D59: 12221.11
A60: TOTAL EXPENSES | B60: 50198.8 | C60: 57325.95 | D60: 64391.12
... A75: Basic EPS — Continuing Ops (₹) | B75: 15.98 | C75: 15.78 | D75: 16.52
A76: CASH FLOW STATEMENT
A77: PBT from Continuing Operations | B77: 26400.28 | C77: 26926.94 | D77: 28033.39
A78: Depreciation & Amortization (CFS adj) | B78: 1816.39 | C78: 1950.58 | D78: 1710.53
A79: Finance Costs (CFS adj) | B79: 45.96 | C79: 50.01 | D79: 85.17
A80: Interest Income (CFS adj) | B80: 1710.51 | C80: 1510.46 | D80: 1462.23
A81: Working Capital Changes — Net | B81: 3337.03 | C81: 2742 | D81: 2762.28
A82: Cash Generated from Operations | B82: 23298.42 | C82: 23977.24 | D82: 24837.92
A83: Income Tax Paid | B83: 6119.56 | C83: 6350.2 | D83: 6373.61
A84: NET CASH FROM OPERATING ACTIVITIES (CFO) | B84: 17178.86 | C84: 17627.04 | D84: 18464.31
A85: Capex (PPE + Intangibles) | B85: 3562.53 | C85: 2278.7 | D85: 2182.89
A86: Purchase of Investments (Net) | B86: 1035.71 | C86: 82.67 | D86: 2415.17
A87: Interest & Dividends Received | B87: 1150 | C87: 1109.95 | D87: 947.46
A88: NET CASH FROM INVESTING ACTIVITIES (CFI) | B88: 1562.77 | C88: 395.82 | D88: 2320.74
... A96: CLOSING CASH & EQUIVALENTS | B96: 596.58 | C96: 622.38 | D96: 618.83

Sheet Comparative BS
A1: ITC LIMITED — Comparative Balance Sheet (₹ in Crores)
A2: Particulars | B2: FY2024 (₹ Cr) | C2: FY2025 (₹ Cr) | D2: FY2026 (₹ Cr) | E2: Change FY24→FY25 (₹ Cr) | F2: Change FY25→FY26 (₹ Cr)
A4: NON-CURRENT ASSETS
A5: Property, Plant and Equipment | B5: 23082.33 | C5: 17428.89 | D5: 17471.2 | E5: =C5-B5 -> -5653.44 | F5: =D5-C5 -> 42.31
A6: Capital Work-in-Progress | B6: 2851.14 | C6: 1087.6 | D6: 1499.41 | E6: =C6-B6 -> -1763.54 | F6: =D6-C6 -> 411.81
A7: Investment Property | B7: 340.93 | C7: 322.4 | D7: 303.36 | E7: =C7-B7 -> -18.53 | F7: =D7-C7 -> -19.04
A8: Goodwill | B8: 779.73 | C8: 896.93 | D8: 993.29 | E8: =C8-B8 -> 117.2 | F8: =D8-C8 -> 96.36
A9: Other Intangible Assets | B9: 2678.11 | C9: 2724.74 | D9: 3173.66 | E9: =C9-B9 -> 46.63 | F9: =D9-C9 -> 448.92
A10: Intangible Assets Under Development | B10: 9.64 | C10: 3.31 | D10: 102.47 | E10: =C10-B10 -> -6.33 | F10: =D10-C10 -> 99.16
A11: Right-of-use Assets | B11: 939.12 | C11: 581.89 | D11: 501.02 | E11: =C11-B11 -> -357.23 | F11: =D11-C11 -> -80.87
A12: Investments (Equity Method) | B12: 549.73 | C12: 4711.78 | D12: 5288.24 | E12: =C12-B12 -> 4162.05 | F12: =D12-C12 -> 576.46
A13: Non-current Financial Assets | B13: 18032.91 | C13: 15285.71 | D13: 12437.64 | E13: =C13-B13 -> -2747.2 | F13: =D13-C13 -> -2848.07
A14: Deferred Tax Assets (Net) | B14: 72.19 | C14: 87.98 | D14: 155.18 | E14: =C14-B14 -> 15.79 | F14: =D14-C14 -> 67.2
A15: Income Tax Assets (Net) | B15: 44.93 | C15: 50.24 | D15: 70.05 | E15: =C15-B15 -> 5.31 | F15: =D15-C15 -> 19.81
A16: Other Non-current Assets | B16: 1379.86 | C16: 1015.93 | D16: 1088.45 | E16: =C16-B16 -> -363.93 | F16: =D16-C16 -> 72.52
A17: Total Non-current Assets | B17: 50760.62 | C17: 44197.4 | D17: 43083.97 | E17: =C17-B17 -> -6563.22 | F17: =D17-C17 -> -1113.43
A18: CURRENT ASSETS
A19: Inventories | B19: 14152.88 | C19: 15637.56 | D19: 18622.96 | E19: =C19-B19 -> 1484.68 | F19: =D19-C19 -> 2985.4
A20: Biological Assets | B20: 150 | C20: 198.58 | D20: 249.69 | E20: =C20-B20 -> 48.58 | F20: =D20-C20 -> 51.11
A21: Current Investments | B21: 12944.42 | C21: 16287.5 | D21: 20750.64 | E21: =C21-B21 -> 3343.08 | F21: =D21-C21 -> 4463.14
A22: Trade Receivables | B22: 4025.82 | C22: 4719.67 | D22: 3922.86 | E22: =C22-B22 -> 693.85 | F22: =D22-C22 -> -796.81
A23: Cash and Cash Equivalents | B23: 625.89 | C23: 620 | D23: 643.46 | E23: =C23-B23 -> -5.89 | F23: =D23-C23 -> 23.46
A24: Bank Balances (Other) | B24: 6591.79 | C24: 3392.36 | D24: 2365.33 | E24: =C24-B24 -> -3199.43 | F24: =D24-C24 -> -1027.03
A25: Current Loans | B25: 9.81 | C25: 9.51 | D25: 8.52 | E25: =C25-B25 -> -0.3 | F25: =D25-C25 -> -0.99
A26: Other Current Financial Assets | B26: 1181.74 | C26: 1662.32 | D26: 2361.34 | E26: =C26-B26 -> 480.58 | F26: =D26-C26 -> 699.02
A27: Other Current Assets | B27: 1383.19 | C27: 1371.85 | D27: 1783.61 | E27: =C27-B27 -> -11.34 | F27: =D27-C27 -> 411.76
A28: Total Current Assets | B28: 41065.54 | C28: 43893.28 | D28: 50708.41 | E28: =C28-B28 -> 2827.74 | F28: =D28-C28 -> 6815.13
A29: TOTAL ASSETS | B29: 91826.16 | C29: 88090.68 | D29: 93792.38 | E29: =C29-B29 -> -3735.48 | F29: =D29-C29 -> 5701.7
A30: EQUITY
A31: Equity Share Capital | B31: 1248.47 | C31: 1251.41 | D31: 1252.95 | E31: =C31-B31 -> 2.94 | F31: =D31-C31 -> 1.54
A32: Other Equity | B32: 73258.53 | C32: 68778.64 | D32: 71254.35 | E32: =C32-B32 -> -4479.89 | F32: =D32-C32 -> 2475.71
A33: Equity Attr. to Owners of Parent | B33: 74507 | C33: 70030.05 | D33: 72507.3 | E33: =C33-B33 -> -4476.95 | F33: =D33-C33 -> 2477.25
A34: Non-controlling Interests | B34: 382.97 | C34: 367.89 | D34: 365.72 | E34: =C34-B34 -> -15.08 | F34: =D34-C34 -> -2.17
A35: Total Equity | B35: 74889.97 | C35: 70397.94 | D35: 72873.02 | E35: =C35-B35 -> -4492.03 | F35: =D35-C35 -> 2475.08
A36: NON-CURRENT LIABILITIES
A37: Non-current Borrowings | B37: 1.76 | C37: 0 | D37: 60 | E37: =C37-B37 -> -1.76 | F37: =D37-C37 -> 60
A38: Lease Liabilities (NC) | B38: 230.61 | C38: 137.21 | D38: 140.86 | E38: =C38-B38 -> -93.4 | F38: =D38-C38 -> 3.65
A39: Other NC Financial Liabilities | B39: 433.96 | C39: 301.34 | D39: 510.4 | E39: =C39-B39 -> -132.62 | F39: =D39-C39 -> 209.06
A40: Provisions (NC) | B40: 288.3 | C40: 303.11 | D40: 389.43 | E40: =C40-B40 -> 14.81 | F40: =D40-C40 -> 86.32
A41: Deferred Tax Liabilities (Net) | B41: 2141.44 | C41: 2582.46 | D41: 3089.62 | E41: =C41-B41 -> 441.02 | F41: =D41-C41 -> 507.16
A42: Other Non-current Liabilities | B42: 149.72 | C42: 34.51 | D42: 41.78 | E42: =C42-B42 -> -115.21 | F42: =D42-C42 -> 7.27
A43: Total Non-current Liabilities | B43: 3245.79 | C43: 3358.63 | D43: 4232.09 | E43: =C43-B43 -> 112.84 | F43: =D43-C43 -> 873.46
A44: CURRENT LIABILITIES
A45: Current Borrowings | B45: 9.52 | C45: 91.26 | D45: 2126.22 | E45: =C45-B45 -> 81.74 | F45: =D45-C45 -> 2034.96
A46: Lease Liabilities (Current) | B46: 61.54 | C46: 56.07 | D46: 71.98 | E46: =C46-B46 -> -5.47 | F46: =D46-C46 -> 15.91
A47: Trade Payables | B47: 4797.83 | C47: 4807.3 | D47: 5639.55 | E47: =C47-B47 -> 9.47 | F47: =D47-C47 -> 832.25
A48: Other Current Financial Liab. | B48: 2179 | C48: 1921.5 | D48: 2099.15 | E48: =C48-B48 -> -257.5 | F48: =D48-C48 -> 177.65
A49: Other Current Liabilities | B49: 5594.72 | C49: 6148.27 | D49: 5037.64 | E49: =C49-B49 -> 553.55 | F49: =D49-C49 -> -1110.63
A50: Provisions (Current) | B50: 106.91 | C50: 80.06 | D50: 423.91 | E50: =C50-B50 -> -26.85 | F50: =D50-C50 -> 343.85
A51: Current Tax Liabilities (Net) | B51: 940.88 | C51: 1229.65 | D51: 1288.82 | E51: =C51-B51 -> 288.77 | F51: =D51-C51 -> 59.17
A52: Total Current Liabilities | B52: 13690.4 | C52: 14334.11 | D52: 16687.27 | E52: =C52-B52 -> 643.71 | F52: =D52-C52 -> 2353.16
A53: TOTAL EQUITY & LIABILITIES | B53: 91826.16 | C53: 88090.68 | D53: 93792.38 | E53: =C53-B53 -> -3735.48 | F53: =D53-C53 -> 5701.7
A55: Note: All figures in ₹ Crores. Source: ITC Consolidated Annual Reports FY2024, FY2025, FY2026.

Sheet Comparative P&L
A1: ITC LIMITED — Comparative Statement of Profit & Loss (₹ in Crores)
A2: Particulars | B2: FY2024 (₹ Cr) | C2: FY2025 (₹ Cr) | D2: FY2026 (₹ Cr) | E2: Change FY24→FY25 (₹ Cr) | F2: Change FY25→FY26 (₹ Cr)
A4: INCOME
A5: Revenue from Operations | B5: 73891.43 | C5: 81612.78 | D5: 89913.33 | E5: =C5-B5 -> 7721.35 | F5: =D5-C5 -> 8300.55
A6: Other Income | B6: 2693.22 | C6: 2529.69 | D6: 2425.8 | E6: =C6-B6 -> -163.53 | F6: =D6-C6 -> -103.89
A7: Total Income | B7: 76584.65 | C7: 84142.47 | D7: 92339.13 | E7: =C7-B7 -> 7557.82 | F7: =D7-C7 -> 8196.66
A8: EXPENSES
A9: Cost of Materials Consumed | B9: 21288.44 | C9: 23757.33 | D9: 26272.33 | E9: =C9-B9 -> 2468.89 | F9: =D9-C9 -> 2515
A10: Purchases of Stock-in-Trade & Bio. Assets | B10: 6060.13 | C10: 8947.04 | D10: 8826.01 | E10: =C10-B10 -> 2886.91 | F10: =D10-C10 -> -121.03
A11: Changes in Inventories | B11: -367.77 | C11: -725.65 | D11: -2550.46 | E11: =C11-B11 -> -357.88 | F11: =D11-C11 -> -1824.81
A12: Excise Duty | B12: 5959.49 | C12: 6289.44 | D12: 11044.93 | E12: =C12-B12 -> 329.95 | F12: =D12-C12 -> 4755.49
A13: Employee Benefits Expense | B13: 5548.53 | C13: 6169.78 | D13: 6781.5 | E13: =C13-B13 -> 621.25 | F13: =D13-C13 -> 611.72
A14: Finance Costs | B14: 39.11 | C14: 45.06 | D14: 85.17 | E14: =C14-B14 -> 5.95 | F14: =D14-C14 -> 40.11
A15: Depreciation & Amortisation | B15: 1518.05 | C15: 1646.32 | D15: 1710.53 | E15: =C15-B15 -> 128.27 | F15: =D15-C15 -> 64.21
A16: Other Expenses | B16: 10152.82 | C16: 11196.63 | D16: 12221.11 | E16: =C16-B16 -> 1043.81 | F16: =D16-C16 -> 1024.48
A17: Total Expenses | B17: 50198.8 | C17: 57325.95 | D17: 64391.12 | E17: =C17-B17 -> 7127.15 | F17: =D17-C17 -> 7065.17
A18: Share of Profit of Associates & JVs | B18: 14.43 | C18: 110.42 | D18: 377.08 | E18: =C18-B18 -> 95.99 | F18: =D18-C18 -> 266.66
A19: Profit Before Exceptional Items & Tax | B19: 26400.28 | C19: 26926.94 | D19: 28325.09 | E19: =C19-B19 -> 526.66 | F19: =D19-C19 -> 1398.15
A20: Exceptional Items | B20: 0 | C20: 0 | D20: -291.7 | E20: =C20-B20 -> 0 | F20: =D20-C20 -> -291.7
... A28: Total Comprehensive Income | B28: 23707.02 | C28: 34427.62 | D28: 20374.86 | E28: =C28-B28 -> 10720.6 | F28: =D28-C28 -> -14052.76
A30: Note: All figures in ₹ Crores. Source: ITC Consolidated Annual Reports FY2024, FY2025, FY2026.

Sheet Common-Size BS
A1: ITC LIMITED — Common-Size Balance Sheet (% of Total Assets)
A2: Particulars | B2: FY2024 (₹ Cr) | C2: FY2024 (%) | D2: FY2025 (₹ Cr) | E2: FY2025 (%) | F2: FY2026 (₹ Cr) | G2: FY2026 (%)
A4: NON-CURRENT ASSETS
A5: Property, Plant and Equipment | B5: 23082.33 | C5: =B5/B29 -> 0.25136987 | D5: 17428.89 | E5: =D5/D29 -> 0.19785169 | F5: 17471.2 | G5: =F5/F29 -> 0.18627526
A6: Capital Work-in-Progress | B6: 2851.14 | C6: =B6/B29 -> 0.031049322 | D6: 1087.6 | E6: =D6/D29 -> 0.012346369 | F6: 1499.41 | G6: =F6/F29 -> 0.01598648
A7: Investment Property | B7: 340.93 | C7: =B7/B29 -> 0.0037127764 | D7: 322.4 | E7: =D7/D29 -> 0.003659865 | F7: 303.36 | G7: =F7/F29 -> 0.0032343779
A8: Goodwill | B8: 779.73 | C8: =B8/B29 -> 0.0084913711 | D8: 896.93 | E8: =D8/D29 -> 0.010181894 | F8: 993.29 | G8: =F8/F29 -> 0.010590306
A9: Other Intangible Assets | B9: 2678.11 | C9: =B9/B29 -> 0.029165 | D9: 2724.74 | E9: =D9/D29 -> 0.030931081 | F9: 3173.66 | G9: =F9/F29 -> 0.033837077
A10: Intangible Assets Under Development | B10: 9.64 | C10: =B10/B29 -> 0.00010498098 | D10: 3.31 | E10: =D10/D29 -> 3.7574917e-05 | F10: 102.47 | G10: =F10/F29 -> 0.0010925195
A11: Right-of-use Assets | B11: 939.12 | C11: =B11/B29 -> 0.010227151 | D11: 581.89 | E11: =D11/D29 -> 0.0066055796 | F11: 501.02 | G11: =F11/F29 -> 0.0053417986
A12: Investments (Equity Method) | B12: 549.73 | C12: =B12/B29 -> 0.0059866382 | D12: 4711.78 | E12: =D12/D29 -> 0.053487838 | F12: 5288.24 | G12: =F12/F29 -> 0.056382405
A13: Non-current Financial Assets | B13: 18032.91 | C13: =B13/B29 -> 0.19638097 | D13: 15285.71 | E13: =D13/D29 -> 0.17352244 | F13: 12437.64 | G13: =F13/F29 -> 0.13260821
A14: Deferred Tax Assets (Net) | B14: 72.19 | C14: =B14/B29 -> 0.00078615941 | D14: 87.98 | E14: =D14/D29 -> 0.00099874357 | F14: 155.18 | G14: =F14/F29 -> 0.0016545054
A15: Income Tax Assets (Net) | B15: 44.93 | C15: =B15/B29 -> 0.00048929412 | D15: 50.24 | E15: =D15/D29 -> 0.0005703214 | F15: 70.05 | G15: =F15/F29 -> 0.00074686238
A16: Other Non-current Assets | B16: 1379.86 | C16: =B16/B29 -> 0.015026873 | D16: 1015.93 | E16: =D16/D29 -> 0.011532775 | F16: 1088.45 | G16: =F16/F29 -> 0.011604887
A17: Total Non-current Assets | B17: 50760.62 | C17: =B17/B29 -> 0.5527904 | D17: 44197.4 | E17: =D17/D29 -> 0.50172618 | F17: 43083.97 | G17: =F17/F29 -> 0.45935469
A18: CURRENT ASSETS
A19: Inventories | B19: 14152.88 | C19: =B19/B29 -> 0.15412688 | D19: 15637.56 | E19: =D19/D29 -> 0.17751662 | F19: 18622.96 | G19: =F19/F29 -> 0.19855515
A20: Biological Assets | B20: 150 | C20: =B20/B29 -> 0.0016335214 | D20: 198.58 | E20: =D20/D29 -> 0.002254268 | F20: 249.69 | G20: =F20/F29 -> 0.0026621566
A21: Current Investments | B21: 12944.42 | C21: =B21/B29 -> 0.14096658 | D21: 16287.5 | E21: =D21/D29 -> 0.1848947 | F21: 20750.64 | G21: =F21/F29 -> 0.22124015
A22: Trade Receivables | B22: 4025.82 | C22: =B22/B29 -> 0.043841755 | D22: 4719.67 | E22: =D22/D29 -> 0.053577405 | F22: 3922.86 | G22: =F22/F29 -> 0.041824933
A23: Cash and Cash Equivalents | B23: 625.89 | C23: =B23/B29 -> 0.0068160315 | D23: 620 | E23: =D23/D29 -> 0.007038202 | F23: 643.46 | G23: =F23/F29 -> 0.006860472
A24: Bank Balances (Other) | B24: 6591.79 | C24: =B24/B29 -> 0.071785535 | D24: 3392.36 | E24: =D24/D29 -> 0.038509863 | F24: 2365.33 | G24: =F24/F29 -> 0.025218786
A25: Current Loans | B25: 9.81 | C25: =B25/B29 -> 0.0001068323 | D25: 9.51 | E25: =D25/D29 -> 0.00010795694 | F25: 8.52 | G25: =F25/F29 -> 9.0838936e-05
A26: Other Current Financial Assets | B26: 1181.74 | C26: =B26/B29 -> 0.012869317 | D26: 1662.32 | E26: =D26/D29 -> 0.018870555 | F26: 2361.34 | G26: =F26/F29 -> 0.025176246
A27: Other Current Assets | B27: 1383.19 | C27: =B27/B29 -> 0.015063137 | D27: 1371.85 | E27: =D27/D29 -> 0.015573157 | F27: 1783.61 | G27: =F27/F29 -> 0.019016577
A28: Total Current Assets | B28: 41065.54 | C28: =B28/B29 -> 0.4472096 | D28: 43893.28 | E28: =D28/D29 -> 0.49827382 | F28: 50708.41 | G28: =F28/F29 -> 0.54064531
A29: TOTAL ASSETS | B29: 91826.16 | C29: =B29/B29 -> 1 | D29: 88090.68 | E29: =D29/D29 -> 1 | F29: 93792.38 | G29: =F29/F29 -> 1
A30: EQUITY
A31: Equity Share Capital | B31: 1248.47 | C31: =B31/B29 -> 0.013596017 | D31: 1251.41 | E31: =D31/D29 -> 0.01420593 | F31: 1252.95 | G31: =F31/F29 -> 0.013358761
A32: Other Equity | B32: 73258.53 | C32: =B32/B29 -> 0.79779586 | D32: 68778.64 | E32: =D32/D29 -> 0.78077091 | F32: 71254.35 | G32: =F32/F29 -> 0.75970297
A33: Equity Attr. to Owners of Parent | B33: 74507 | C33: =B33/B29 -> 0.81139187 | D33: 70030.05 | E33: =D33/D29 -> 0.79497684 | F33: 72507.3 | G33: =F33/F29 -> 0.77306173
A34: Non-controlling Interests | B34: 382.97 | C34: =B34/B29 -> 0.004170598 | D34: 367.89 | E34: =D34/D29 -> 0.0041762647 | F34: 365.72 | G34: =F34/F29 -> 0.0038992507
A35: Total Equity | B35: 74889.97 | C35: =B35/B29 -> 0.81556247 | D35: 70397.94 | E35: =D35/D29 -> 0.7991531 | F35: 72873.02 | G35: =F35/F29 -> 0.77696099
A36: NON-CURRENT LIABILITIES
A37: Non-current Borrowings | B37: 1.76 | C37: =B37/B29 -> 1.9166651e-05 | D37: 0 | F37: 60 | G37: =F37/F29 -> 0.00063971082
A38: Lease Liabilities (NC) | B38: 230.61 | C38: =B38/B29 -> 0.0025113758 | D38: 137.21 | E38: =D38/D29 -> 0.0015575995 | F38: 140.86 | G38: =F38/F29 -> 0.0015018278
A39: Other NC Financial Liabilities | B39: 433.96 | C39: =B39/B29 -> 0.0047258864 | D39: 301.34 | E39: =D39/D29 -> 0.0034207932 | F39: 510.4 | G39: =F39/F29 -> 0.0054418067
A40: Provisions (NC) | B40: 288.3 | C40: =B40/B29 -> 0.0031396282 | D40: 303.11 | E40: =D40/D29 -> 0.0034408861 | F40: 389.43 | G40: =F40/F29 -> 0.0041520431
A41: Deferred Tax Liabilities (Net) | B41: 2141.44 | C41: =B41/B29 -> 0.023320588 | D41: 2582.46 | E41: =D41/D29 -> 0.029315928 | F41: 3089.62 | G41: =F41/F29 -> 0.032941056
A42: Other Non-current Liabilities | B42: 149.72 | C42: =B42/B29 -> 0.0016304722 | D42: 34.51 | E42: =D42/D29 -> 0.0003917554 | F42: 41.78 | G42: =F42/F29 -> 0.00044545197
A43: Total Non-current Liabilities | B43: 3245.79 | C43: =B43/B29 -> 0.035347117 | D43: 3358.63 | E43: =D43/D29 -> 0.038126962 | F43: 4232.09 | G43: =F43/F29 -> 0.045121896
A44: CURRENT LIABILITIES
A45: Current Borrowings | B45: 9.52 | C45: =B45/B29 -> 0.00010367416 | D45: 91.26 | E45: =D45/D29 -> 0.0010359779 | F45: 2126.22 | G45: =F45/F29 -> 0.022669432
A46: Lease Liabilities (Current) | B46: 61.54 | C46: =B46/B29 -> 0.00067017939 | D46: 56.07 | E46: =D46/D29 -> 0.0006365032 | F46: 71.98 | G46: =F46/F29 -> 0.00076743974
A47: Trade Payables | B47: 4797.83 | C47: =B47/B29 -> 0.052249054 | D47: 4807.3 | E47: =D47/D29 -> 0.054572175 | F47: 5639.55 | G47: =F47/F29 -> 0.060128019
A48: Other Current Financial Liab. | B48: 2179 | C48: =B48/B29 -> 0.023729621 | D48: 1921.5 | E48: =D48/D29 -> 0.02181275 | F48: 2099.15 | G48: =F48/F29 -> 0.022380816
A49: Other Current Liabilities | B49: 5594.72 | C49: =B49/B29 -> 0.0609273 | D49: 6148.27 | E49: =D49/D29 -> 0.069794784 | F49: 5037.64 | G49: =F49/F29 -> 0.053710547
A50: Provisions (Current) | B50: 106.91 | C50: =B50/B29 -> 0.0011642652 | D50: 80.06 | E50: =D50/D29 -> 0.00090883621 | F50: 423.91 | G50: =F50/F29 -> 0.0045196635
A51: Current Tax Liabilities (Net) | B51: 940.88 | C51: =B51/B29 -> 0.010246318 | D51: 1229.65 | E51: =D51/D29 -> 0.013958911 | F51: 1288.82 | G51: =F51/F29 -> 0.013741202
A52: Total Current Liabilities | B52: 13690.4 | C52: =B52/B29 -> 0.14909041 | D52: 14334.11 | E52: =D52/D29 -> 0.16271994 | F52: 16687.27 | G52: =F52/F29 -> 0.17791712
A53: TOTAL EQUITY & LIABILITIES | B53: 91826.16 | C53: =B53/B29 -> 1 | D53: 88090.68 | E53: =D53/D29 -> 1 | F53: 93792.38 | G53: =F53/F29 -> 1
A55: Note: % calculated as each line item as a proportion of Total Assets. Source: ITC Consolidated Annual Reports.

Sheet Common-Size P&L
A1: ITC LIMITED — Common-Size Statement of Profit & Loss (% of Total Income)
A2: Particulars | B2: FY2024 (₹ Cr) | C2: FY2024 (%) | D2: FY2025 (₹ Cr) | E2: FY2025 (%) | F2: FY2026 (₹ Cr) | G2: FY2026 (%)
A4: INCOME
A5: Revenue from Operations | B5: 73891.43 | C5: =B5/B7 -> 0.96483342 | D5: 81612.78 | E5: =D5/D7 -> 0.96993563 | F5: 89913.33 | G5: =F5/F7 -> 0.97372945
A6: Other Income | B6: 2693.22 | C6: =B6/B7 -> 0.035166577 | D6: 2529.69 | E6: =D6/D7 -> 0.030064366 | F6: 2425.8 | G6: =F6/F7 -> 0.026270553
A7: Total Income | B7: 76584.65 | C7: =B7/B7 -> 1 | D7: 84142.47 | E7: =D7/D7 -> 1 | F7: 92339.13 | G7: =F7/F7 -> 1
A8: EXPENSES
A9: Cost of Materials Consumed | B9: 21288.44 | C9: =B9/B7 -> 0.27797267 | D9: 23757.33 | E9: =D9/D7 -> 0.28234648 | F9: 26272.33 | G9: =F9/F7 -> 0.28452001
A10: Purchases of Stock-in-Trade & Bio. Assets | B10: 6060.13 | C10: =B10/B7 -> 0.079129826 | D10: 8947.04 | E10: =D10/D7 -> 0.10633203 | F10: 8826.01 | G10: =F10/F7 -> 0.095582555
A11: Changes in Inventories | B11: -367.77 | C11: =B11/B7 -> -0.0048021372 | D11: -725.65 | E11: =D11/D7 -> -0.0086240634 | F11: -2550.46 | G11: =F11/F7 -> -0.027620576
A12: Excise Duty | B12: 5959.49 | C12: =B12/B7 -> 0.077815724 | D12: 6289.44 | E12: =D12/D7 -> 0.074747509 | F12: 11044.93 | G12: =F12/F7 -> 0.11961267
A13: Employee Benefits Expense | B13: 5548.53 | C13: =B13/B7 -> 0.072449636 | D13: 6169.78 | E13: =D13/D7 -> 0.073325397 | F13: 6781.5 | G13: =F13/F7 -> 0.073441238
A14: Finance Costs | B14: 39.11 | C14: =B14/B7 -> 0.00051067675 | D14: 45.06 | E14: =D14/D7 -> 0.00053552029 | F14: 85.17 | G14: =F14/F7 -> 0.00092236087
A15: Depreciation & Amortisation | B15: 1518.05 | C15: =B15/B7 -> 0.019821857 | D15: 1646.32 | E15: =D15/D7 -> 0.019565863 | F15: 1710.53 | G15: =F15/F7 -> 0.018524433
A16: Other Expenses | B16: 10152.82 | C16: =B16/B7 -> 0.13256991 | D16: 11196.63 | E16: =D16/D7 -> 0.13306752 | F16: 12221.11 | G16: =F16/F7 -> 0.13235028
A17: Total Expenses | B17: 50198.8 | C17: =B17/B7 -> 0.65546816 | D17: 57325.95 | E17: =D17/D7 -> 0.68129626 | F17: 64391.12 | G17: =F17/F7 -> 0.69733297
A18: Share of Profit of Associates & JVs | B18: 14.43 | C18: =B18/B7 -> 0.00018841896 | D18: 110.42 | E18: =D18/D7 -> 0.0013122981 | F18: 377.08 | G18: =F18/F7 -> 0.0040836425
A19: Profit Before Exceptional Items & Tax | B19: 26400.28 | C19: =B19/B7 -> 0.34472025 | D19: 26926.94 | E19: =D19/D7 -> 0.32001604 | F19: 28325.09 | G19: =F19/F7 -> 0.30675067
A20: Exceptional Items | B20: 0 | C20: =B20/B7 -> 0 | D20: 0 | E20: =D20/D7 -> 0 | F20: -291.7 | G20: =F20/F7 -> -0.0031590075
A21: Profit Before Tax (Continuing Ops) | B21: 26400.28 | C21: =B21/B7 -> 0.34472025 | D21: 26926.94 | E21: =D21/D7 -> 0.32001604 | F21: 28033.39 | G21: =F21/F7 -> 0.30359166
A22: Current Tax | B22: 6017.21 | C22: =B22/B7 -> 0.0785694 | D22: 6509.61 | E22: =D22/D7 -> 0.077364142 | F22: 6412.97 | G22: =F22/F7 -> 0.069450189
A23: Deferred Tax | B23: 192.25 | C23: =B23/B7 -> 0.0025102942 | D23: 380.86 | E23: =D23/D7 -> 0.0045263706 | F23: 602.27 | G23: =F23/F7 -> 0.0065223703
A24: Profit for Year (Continuing Ops) | B24: 20190.82 | C24: =B24/B7 -> 0.26364056 | D24: 20036.47 | E24: =D24/D7 -> 0.23812553 | F24: 21018.15 | G24: =F24/F7 -> 0.2276191
A25: Profit from Discontinued Operations (Net) | B25: 560.54 | C25: =B25/B7 -> 0.0073192213 | D25: 15016.01 | E25: =D25/D7 -> 0.17845934 | F25: 0 | G25: =F25/F7 -> 0
A26: Profit for the Year | B26: 20751.36 | C26: =B26/B7 -> 0.27095978 | D26: 35052.48 | E26: =D26/D7 -> 0.41658487 | F26: 21018.15 | G26: =F26/F7 -> 0.2276191
A27: Other Comprehensive Income (Net) | B27: 2955.66 | C27: =B27/B7 -> 0.038593373 | D27: -624.86 | E27: =D27/D7 -> -0.0074262141 | F27: -643.29 | G27: =F27/F7 -> -0.0069666023
A28: Total Comprehensive Income | B28: 23707.02 | C28: =B28/B7 -> 0.30955315 | D28: 34427.62 | E28: =D28/D7 -> 0.40915866 | F28: 20374.86 | G28: =F28/F7 -> 0.2206525
A30: Note: % calculated as proportion of Total Income (Revenue from Ops + Other Income). Source: ITC Consolidated Annual Reports.

Sheet Trend Analysis
A1: ITC LIMITED — Trend Analysis (Base Year = FY2024, Index = 100)
A2: Key Indicator | B2: FY2024 (Base = 100) | C2: FY2025 Index | D2: FY2026 Index | E2: YoY % Change (FY25→FY26)
A4: ── BALANCE SHEET ──
A5: Total Assets | B5: 100 | C5: 95.93 | D5: 102.14 | E5: 6.47
A6: Total Equity | B6: 100 | C6: 94 | D6: 97.31 | E6: 3.52
A7: Total Non-current Assets | B7: 100 | C7: 87.07 | D7: 84.88 | E7: -2.52
A8: Total Current Assets | B8: 100 | C8: 106.89 | D8: 123.48 | E8: 15.53
A9: Inventories | B9: 100 | C9: 110.49 | D9: 131.58 | E9: 19.09
A10: Current Investments | B10: 100 | C10: 125.83 | D10: 160.31 | E10: 27.4
A11: Total NCL | B11: 100 | C11: 103.48 | D11: 130.39 | E11: 26.01
A12: Total Current Liabilities | B12: 100 | C12: 104.7 | D12: 121.89 | E12: 16.42
A13: Property, Plant & Equipment | B13: 100 | C13: 75.51 | D13: 75.69 | E13: 0.24
A14: ── PROFIT & LOSS ──
A15: Revenue from Operations | B15: 100 | C15: 110.45 | D15: 121.68 | E15: 10.17
A16: Total Income | B16: 100 | C16: 109.87 | D16: 120.57 | E16: 9.74
A17: Total Expenses | B17: 100 | C17: 114.2 | D17: 128.27 | E17: 12.32
A18: EBIT (PBT + Finance Costs) | B18: 100 | C18: 102.01 | D18: 106.35 | E18: 4.25
A19: Profit Before Tax | B19: 100 | C19: 101.99 | D19: 106.19 | E19: 4.11
A20: Profit for the Year | B20: 100 | C20: 168.92 | D20: 101.29 | E20: -40.04
A21: Employee Benefits Expense | B21: 100 | C21: 111.2 | D21: 122.22 | E21: 9.91
A22: Finance Costs | B22: 100 | C22: 115.21 | D22: 217.77 | E22: 89.01
A23: ── KEY RATIOS ──
A24: Net Profit Margin (%) | B24: 100 | C24: 153.74 | D24: 84 | E24: -45.36
A25: Return on Equity (%) | B25: 100 | C25: 179.69 | D25: 104.09 | E25: -42.07
A26: Current Ratio (x) | B26: 2.9996 | C26: 3.0622 | D26: 3.0387 | E26: -0.76
A27: Asset Turnover (x) | B27: 0.8047 | C27: 0.9265 | D27: 0.9586 | E27: 3.47
A28: Debt-to-Equity (x) | B28: 0.2261 | C28: 0.2513 | D28: 0.2871 | E28: 14.22
A29: Revenue/Employee Exp (x) | B29: 13.3173 | C29: 13.2278 | D29: 13.2586 | E29: 0.23
A31: Note: Index values calculated as (Current Year Value / FY2024 Base Value) × 100. Ratios are actuals, not indexed.

Sheet Interpretation
A1: ITC LIMITED — Financial Analysis: Key Observations & Interpretation (FY2024–FY2026)
A3: COMPARATIVE BALANCE SHEET
A4: 1. Total Assets
A5: Trend | B5: Total Assets declined from ₹91,826 Cr (FY24) to ₹88,091 Cr (FY25) — a fall of ~4.1% — before recovering to ₹93,792 Cr in FY26 (+6.5%). The FY25 dip was driven by a large reduction in PP&E (₹23,082 Cr → ₹17,429 Cr), likely reflecting block disposals or impairments tied to the Hotels demerger.
A6: 2. Equity Erosion (FY25) & Recovery (FY26) | B6: Total Equity fell from ₹74,890 Cr (FY24) to ₹70,398 Cr (FY25), a drop of ~6%, primarily due to a sharp reduction in Other Equity (₹73,259 Cr → ₹68,779 Cr). This suggests dividend payouts and/or buybacks exceeded retained profits in FY25. In FY26 equity partially recovered to ₹72,873 Cr.
A7: 3. Asset Mix Shift: NCA vs CA | B7: Non-current Assets shrank from ₹50,761 Cr to ₹44,197 Cr (FY25) and further to ₹43,084 Cr (FY26), while Current Assets expanded from ₹41,066 Cr to ₹43,893 Cr to ₹50,708 Cr. The rising share of current assets (from 44.7% to 54.1% of Total Assets) points to higher working capital intensity and growing liquid investments.
A8: 4. Surge in Current Investments (FY26) | B8: Current Investments jumped from ₹12,944 Cr (FY24) to ₹20,751 Cr (FY26) — a 60% rise — showing ITC is parking significant surplus cash in liquid mutual funds/bonds rather than deploying it in capex or M&A.
A9: 5. Borrowings Nearly Zero | B9: ITC is virtually debt-free. Total borrowings (current + non-current) were just ₹2,186 Cr in FY26 (vs ₹11.28 Cr in FY24), placing it in an extremely low-leverage position. Finance costs have risen sharply (₹39 Cr → ₹85 Cr) but remain negligible relative to earnings.
A10: COMPARATIVE P&L
A11: 6. Robust Revenue Growth | B11: Revenue from Operations grew at a healthy CAGR of ~10.2% over FY24–FY26: ₹73,891 Cr → ₹81,613 Cr → ₹89,913 Cr. This reflects volume and value growth across FMCG, Agribusiness, and Paperboards segments even as the Hotels business was demerged.
A12: 7. Rising Cost Pressure (Total Expenses) | B12: Total Expenses grew faster than revenue: from ₹50,199 Cr (65.5% of income) to ₹64,391 Cr (69.7% of income) in FY26. Material costs (₹26,272 Cr, excl. purchase of stock-in-trade: ₹8,826 Cr) and Excise Duty (₹11,045 Cr) are the dominant drivers. Operating leverage is being compressed.
A13: 8. PAT Anomaly in FY25 | B13: Profit for the Year spiked to ₹35,052 Cr in FY25 from ₹20,751 Cr in FY24 due to exceptional profits from discontinued operations (Hotels demerger: ₹15,128 Cr exceptional income, net of tax). FY26 PAT normalised to ₹21,018 Cr — broadly in line with FY24, underscoring the one-time nature of the FY25 gain.
A14: 9. Profit Before Tax (Continuing Ops) — Steady Growth | B14: PBT from continuing operations grew steadily: ₹26,400 Cr → ₹26,927 Cr → ₹28,033 Cr. This indicates core business profitability is intact and growing at ~3% CAGR, though slower than revenue growth due to cost inflation.
A15: 10. Finance Cost Spike (FY26) | B15: Finance costs nearly doubled from ₹45 Cr (FY25) to ₹85 Cr (FY26), largely due to the ₹2,126 Cr in current borrowings (vs ₹91 Cr in FY25). Still immaterial relative to earnings, but worth monitoring.
A16: COMMON-SIZE ANALYSIS
A17: 11. Declining Material Cost % (as % Total Income) | B17: Material cost (consumed) as a % of Total Income rose from 27.8% to 28.5% — a 70 bps adverse movement. However, Purchases of Stock-in-Trade fell from 7.9% to 9.6% in FY25 and then to 9.6% in FY26, partly offset by inventory buildup (negative change-in-inventory ₹2,550 Cr in FY26 = stock accumulation).
A18: 12. Excise Duty Weight Rising | B18: Excise duty jumped from 7.8% (FY24) to 11.9% (FY26) of Total Income — a structural headwind for the cigarettes business, reflecting government policy. This compresses PAT margins when not fully passed on.
A19: 13. Employee Cost Stable at ~7% | B19: Employee benefit expense remained roughly stable at 7.3% of Total Income across all three years, indicating good productivity management despite inflationary pressures on salaries.
A20: 14. Equity Dominant Financing (>77%) | B20: Common-size BS shows Equity at 77.7% of Total Assets in FY26 (down from 81.5% in FY24), confirming ITC's conservative capital structure. Debt is under 3% of the balance sheet — a company almost entirely financed by its own profits.
A21: TREND ANALYSIS
A22: 15. Revenue Index FY26 = ~122 (Base FY24 = 100) | B22: Revenue has grown strongly — +21.7% over two years. Expenses grew at an even faster clip (index ~128), compressing operating margins. Net profit index (FY26 = ~101) confirms normalised profitability is back to FY24 levels post the Hotels windfall in FY25.
A23: 16. Current Ratio Improving | B23: Current ratio improved from 3.00x (FY24) to 3.06x (FY25) to 3.04x (FY26) — well above the safety threshold of 1.5x. Reflects strong liquidity with substantial liquid investments in current assets.
A24: 17. Asset Turnover Inching Up | B24: Asset turnover improved from 0.80x to 0.93x to 0.96x, meaning ITC is generating more revenue per rupee of assets deployed — a positive efficiency signal. As the Hotels segment (capital-heavy, lower turnover) is now demerged, this metric should continue to improve.
A25: 18. Net Profit Margin Compressed | B25: Net Profit Margin (PAT/Total Income) normalised to 22.8% in FY26 (FY24: 27.1%, FY25: 41.7% due to Hotels exceptional). The FY24 baseline margin itself is under pressure in FY26 — 22.8% vs 27.1% — due to rising excise duty and material costs. This is the most important watch metric.
A26: 19. Finance Cost Rising — Still Negligible | B26: Finance costs index jumped to 218 (FY26 vs FY24 base), but at ₹85 Cr it represents just 0.09% of revenue. Not yet a concern, but signals the company has taken on some short-term working capital borrowings in FY26 — likely to fund inventory build (₹18,623 Cr vs ₹14,153 Cr in FY24).
A27: OVERALL CONCLUSION
A28: Summary | B28: ITC remains one of India's most financially robust consumer goods conglomerates. Revenue growth is strong and consistent. The Hotels demerger in FY25 was value-accretive and has freed up capital. The company is cash-rich, nearly debt-free, and generating strong free cash flows deployed into liquid investments. Key risks to watch: (a) rising excise duty on cigarettes compressing FMCG margins, (b) material cost inflation, and (c) still-modest FMCG profitability beyond the cigarettes engine. The normalisation of PAT in FY26 is expected and does not signal structural weakness — the FY25 spike was a one-time demerger gain.
A30: Prepared by: Financial Analysis | Source: ITC Consolidated Annual Reports FY2024, FY2025, FY2026

Sheet Cover (2)
B3: ITC Limited — Comparable Company Analysis (CCA)
B4: Method 2 Valuation — Financial Statement Analysis Project
B6: Prepared per Project Guidelines Section 6, Method 2: implied valuation using EV/EBITDA, EV/EBIT, P/E and EV/Revenue multiples across a 4-company peer group.
B9: Company Valued | C9: ITC Limited (NSE: ITC | BSE: 500875)
B11: Peer Group (4 companies) | C11: Hindustan Unilever Ltd. · Godfrey Phillips India Ltd. · Nestlé India Ltd. · Britannia Industries Ltd.
B13: Basis | C13: FY2025-26 (year ended 31 March 2026) reported financials; market data as of August 2026
B15: Currency / Units | C15: ₹ Crore unless stated otherwise
B17: Source | C17: Company FY26 results releases, Screener.in, and other public filings/press coverage — see Sources tab for line-by-line citations
B20: Tab Guide
B22: Peer Data | C22: Raw inputs for ITC and each of the 4 peers: Revenue, EBITDA, EBIT, Net Income, Market Cap, Net Debt, Enterprise Value, EPS — with source and as-of date for every line.
B23: CCA Multiples | C23: EV/Revenue, EV/EBITDA, EV/EBIT and P/E computed for every company; Mean / Median / Min / Max computed across the 4-peer group only.
B24: Implied Valuation | C24: Peer multiples applied to ITC's own metrics to derive an implied Enterprise Value and implied price per share under each multiple and statistic — the ‘football field’ valuation range.
B25: Sources & Notes | C25: Full citation log and every simplifying assumption made, in the same spirit as the Assumptions Log in the companion DCF workbook.
B28: Colour convention: BLUE = hardcoded input/source data · BLACK = formula · GREEN = cross-sheet link.
B30: Academic exercise — not investment advice. Market data reflects a point-in-time snapshot (August 2026) compiled from public secondary sources; refresh before relying on it for any live decision.

Sheet Peer Data
B2: Peer Data — Inputs
B3: All figures ₹ Crore unless stated. FY2025-26 (year ended 31 March 2026) reported financials; market data as of August 2026.
B5: Company | C5: Revenue | D5: EBITDA | E5: EBIT | F5: Net Income | G5: Total Debt | H5: Cash & Investments | I5: Shares O/S (Cr) | J5: Share Price (₹) | K5: Market Cap | L5: Net Debt | M5: Enterprise Value | N5: EPS (₹) | O5: Data As Of | P5: Source
B6: ITC Limited (for reference) | C6: 89913.33 | D6: 27317.91 | E6: 25607.38 | F6: 21018.15 | G6: 2186.22 | H6: 21394.1 | I6: 1252.95 | J6: 278 | K6: =I6*J6 -> 348320.1 | L6: =G6-H6 -> -19207.88 | M6: =K6+L6 -> 329112.22 | N6: =F6/I6 -> 16.774931 | O6: Aug 2026 | P6: Company FY26 Report & Accounts; NSE/BSE closing price ~₹278 (Aug 2026), consistent with Sections 6.5/8 of the FSA report.
B7: Hindustan Unilever Ltd. | C7: 63763 | D7: 15054 | E7: 13721 | F7: 10652 | G7: 14 | H7: 8250 | I7: 234.98 | J7: =K7/I7 -> 2055.9154 | K7: 483099 | L7: =G7-H7 -> -8236 | M7: =K7+L7 -> 474863 | N7: =F7/I7 -> 45.331518 | O7: Aug 2026 | P7: HUL FY26 results release (turnover ₹63,763 Cr, EBITDA ₹15,054 Cr, D&A ₹1,333 Cr, PAT ₹10,652 Cr); Market Cap ₹4,83,099 Cr per Screener.in (Aug 2026); Total Debt/Cash per Simply Wall St balance-sheet summary.
B8: Godfrey Phillips India Ltd. | C8: 6110 | D8: 1335 | E8: 1215 | F8: 1525 | G8: 0 | H8: 0 | I8: 15.6 | J8: =K8/I8 -> 2293.0128 | K8: 35771 | L8: =G8-H8 -> 0 | M8: =K8+L8 -> 35771 | N8: =F8/I8 -> 97.75641 | O8: Aug 2026 | P8: FY26 Net Profit ₹1,525 Cr per company release (InvestyWise); Revenue ₹6,110 Cr and Market Cap ₹35,771 Cr per Screener.in (Aug 2026). EBITDA/EBIT estimated from Q1 FY26 EBITDA margin (~21.9%, pre the FY27 tax-driven margin shock) applied to FY26 revenue — not company-disclosed full-year figures. Net Debt simplified to nil (GPI is disclosed as 'almost debt free' per Screener); precise cash/investment balance not decomposed from available sources.
B9: Nestlé India Ltd. | C9: 24437 | D9: 5670 | E9: 4920 | F9: 3860 | G9: 0 | H9: 0 | I9: 96.42 | J9: =K9/I9 -> 2997.262 | K9: 288996 | L9: =G9-H9 -> 0 | M9: =K9+L9 -> 288996 | N9: =F9/I9 -> 40.033188 | O9: Aug 2026 | P9: Revenue ₹24,437 Cr and Net Profit ₹3,860 Cr per Screener.in (Aug 2026); EBITDA/EBIT estimated from FY26 quarterly EBITDA margins (21-26%, average ~23.2%) applied to FY26 revenue — not a single disclosed full-year figure. Shares outstanding 9.64 Cr (widely reported, face value ₹10); Net Debt simplified to nil (Nestlé India carries negligible debt).
B10: Britannia Industries Ltd. | C10: 19151.59 | D10: 3320.4 | E10: 2990 | F10: 2537.01 | G10: 0 | H10: 0 | I10: 24.07 | J10: =K10/I10 -> 5217.0752 | K10: 125575 | L10: =G10-H10 -> 0 | M10: =K10+L10 -> 125575 | N10: =F10/I10 -> 105.40133 | O10: Aug 2026 | P10: Revenue ₹19,151.59 Cr and Net Profit ₹2,537.01 Cr per company FY26 results (ScanX); TTM EBITDA ₹3,320.4 Cr per Tickertape. EBIT estimated as EBITDA less an assumed ₹330 Cr D&A run-rate. Market Cap ₹1,25,575 Cr per Screener.in (Aug 2026); Net Debt simplified to nil, consistent with Britannia's low-leverage profile.

Sheet CCA Multiples
B2: Trading Multiples
B3: EV/Revenue, EV/EBITDA and EV/EBIT use Enterprise Value; P/E uses Share Price ÷ EPS. Mean / Median / Min / Max are computed across the 4-company peer group only — ITC is shown for reference and excluded from the summary statistics.
B6: Company | C6: EV / Revenue | D6: EV / EBITDA | E6: EV / EBIT | F6: P / E
B7: ='Peer Data'!B6 -> ITC Limited (for reference) | C7: ='Peer Data'!M6/'Peer Data'!C6 -> 3.6603273 | D7: ='Peer Data'!M6/'Peer Data'!D6 -> 12.047489 | E7: ='Peer Data'!M6/'Peer Data'!E6 -> 12.852241 | F7: ='Peer Data'!J6/'Peer Data'!N6 -> 16.572348
B8: ='Peer Data'!B7 -> Hindustan Unilever Ltd. | C8: ='Peer Data'!M7/'Peer Data'!C7 -> 7.4473127 | D8: ='Peer Data'!M7/'Peer Data'!D7 -> 31.543975 | E8: ='Peer Data'!M7/'Peer Data'!E7 -> 34.608483 | F8: ='Peer Data'!J7/'Peer Data'!N7 -> 45.352891
B9: ='Peer Data'!B8 -> Godfrey Phillips India Ltd. | C9: ='Peer Data'!M8/'Peer Data'!C8 -> 5.8545008 | D9: ='Peer Data'!M8/'Peer Data'!D8 -> 26.794757 | E9: ='Peer Data'!M8/'Peer Data'!E8 -> 29.441152 | F9: ='Peer Data'!J8/'Peer Data'!N8 -> 23.456393
B10: ='Peer Data'!B9 -> Nestlé India Ltd. | C10: ='Peer Data'!M9/'Peer Data'!C9 -> 11.826165 | D10: ='Peer Data'!M9/'Peer Data'!D9 -> 50.969312 | E10: ='Peer Data'!M9/'Peer Data'!E9 -> 58.739024 | F10: ='Peer Data'!J9/'Peer Data'!N9 -> 74.86943
B11: ='Peer Data'!B10 -> Britannia Industries Ltd. | C11: ='Peer Data'!M10/'Peer Data'!C10 -> 6.5568968 | D11: ='Peer Data'!M10/'Peer Data'!D10 -> 37.819239 | E11: ='Peer Data'!M10/'Peer Data'!E10 -> 41.998328 | F11: ='Peer Data'!J10/'Peer Data'!N10 -> 49.497243
B12: Peer Group Summary Statistics (4 companies)
B14: Mean | C14: =AVERAGE(C8:C11) -> 7.9212189 | D14: =AVERAGE(D8:D11) -> 36.781821 | E14: =AVERAGE(E8:E11) -> 41.196747 | F14: =AVERAGE(F8:F11) -> 48.293989
B15: Median | C15: =MEDIAN(C8:C11) -> 7.0021048 | D15: =MEDIAN(D8:D11) -> 34.681607 | E15: =MEDIAN(E8:E11) -> 38.303406 | F15: =MEDIAN(F8:F11) -> 47.425067
B16: Min | C16: =MIN(C8:C11) -> 5.8545008 | D16: =MIN(D8:D11) -> 26.794757 | E16: =MIN(E8:E11) -> 29.441152 | F16: =MIN(F8:F11) -> 23.456393
B17: Max | C17: =MAX(C8:C11) -> 11.826165 | D17: =MAX(D8:D11) -> 50.969312 | E17: =MAX(E8:E11) -> 58.739024 | F17: =MAX(F8:F11) -> 74.86943

Sheet Implied Valuation
B2: Implied Valuation of ITC — Comparable Company Analysis
B3: Each peer-group statistic (Mean/Median/Min/Max) from the CCA Multiples tab is applied to ITC's own Revenue, EBITDA, EBIT and EPS to derive an implied price per share under each multiple. EV-based multiples are bridged to equity value using ITC's own FY26 Net Debt; the P/E multiple is applied directly to ITC's EPS.
B5: ITC Inputs (from Peer Data tab)
B6: Revenue (₹ Cr) | C6: ='Peer Data'!C6 -> 89913.33
B7: EBITDA (₹ Cr) | C7: ='Peer Data'!D6 -> 27317.91
B8: EBIT (₹ Cr) | C8: ='Peer Data'!E6 -> 25607.38
B9: EPS (₹) | C9: ='Peer Data'!N6 -> 16.774931
B10: Net Debt (₹ Cr) | C10: ='Peer Data'!L6 -> -19207.88
B11: Shares Outstanding (Cr) | C11: ='Peer Data'!I6 -> 1252.95
B12: Current Share Price (₹) | C12: ='Peer Data'!J6 -> 278
B13: Implied Price per Share (₹) by Multiple and Peer Statistic
B14: Statistic | C14: EV / Revenue | D14: EV / EBITDA | E14: EV / EBIT | F14: P / E | G14: Average (4 multiples)
B15: Mean | C15: =('CCA Multiples'!C14*$C$6-$C$10)/$C$11 -> 583.76715 | D15: =('CCA Multiples'!D14*$C$7-$C$10)/$C$11 -> 817.2795 | E15: =('CCA Multiples'!E14*$C$8-$C$10)/$C$11 -> 857.29569 | F15: ='CCA Multiples'!F14*$C$9 -> 810.12835 | G15: =AVERAGE(C15:F15) -> 767.11767
B16: Median | C16: =('CCA Multiples'!C15*$C$6-$C$10)/$C$11 -> 517.81032 | D16: =('CCA Multiples'!D15*$C$7-$C$10)/$C$11 -> 771.4888 | E16: =('CCA Multiples'!E15*$C$8-$C$10)/$C$11 -> 798.16253 | F16: ='CCA Multiples'!F15*$C$9 -> 795.55224 | G16: =AVERAGE(C16:F16) -> 720.75347
B17: Min | C17: =('CCA Multiples'!C16*$C$6-$C$10)/$C$11 -> 435.45676 | D17: =('CCA Multiples'!D16*$C$7-$C$10)/$C$11 -> 599.5328 | E17: =('CCA Multiples'!E16*$C$8-$C$10)/$C$11 -> 617.03871 | F17: ='CCA Multiples'!F16*$C$9 -> 393.47939 | G17: =AVERAGE(C17:F17) -> 511.37691
B18: Max | C18: =('CCA Multiples'!C17*$C$6-$C$10)/$C$11 -> 863.9912 | D18: =('CCA Multiples'!D17*$C$7-$C$10)/$C$11 -> 1126.6076 | E18: =('CCA Multiples'!E17*$C$8-$C$10)/$C$11 -> 1215.819 | F18: ='CCA Multiples'!F17*$C$9 -> 1255.9295 | G18: =AVERAGE(C18:F18) -> 1115.5868
B20: Football Field Summary
B21: Metric | C21: Value
B22: Low (Min of all implied prices) | C22: =MIN(C15:F18) -> 393.47939
B23: High (Max of all implied prices) | C23: =MAX(C15:F18) -> 1255.9295
B24: Midpoint (Average of Mean-statistic row) | C24: =G15 -> 767.11767
B26: Current Market Price (₹) | C26: =$C$12 -> 278
B27: Implied Upside / (Downside) vs. CCA Midpoint | C27: =C24/C26-1 -> 1.7594161
B28: Memo: DCF Intrinsic Value per Share (companion workbook) | C28: 338.25
B31: Interpretation: The CCA implies a much higher value per share (₹511-1,256 range, ~₹767 midpoint) than both ITC's current market price (₹278) and the companion DCF's intrinsic value (₹338.25). This gap is a real finding, not a modelling error: it is driven almost entirely by the peer group trading at far richer multiples than ITC across every metric — HUL and Nestlé India in particular command P/E multiples in the 45x-85x range versus ITC's ~17x, consistent with the ‘conglomerate/tobacco discount’ already documented in Section 8.4 of the companion FSA report. In other words, the CCA does not suggest ITC is dramatically undervalued in absolute terms; it shows that the market prices ITC's cigarette-linked, diversified earnings mix at a structurally lower multiple than pure-play, high-growth FMCG peers, and that gap would only close if ITC's FMCG-Others business grew large enough within the group to change the market's blended perception — exactly the strategic rationale management has articulated (Section 2.2) for scaling FMCG-Others and demerging Hotels. EV-based multiples (EV/Revenue, EV/EBITDA, EV/EBIT) are generally more reliable for cross-company comparison than P/E, since they are capital-structure-neutral; P/E is included per the Project Guidelines' explicit requirement but should be weighted cautiously given ITC's and its peers' very different leverage and non-operating-asset profiles. The Min/Max rows are single-peer-driven and should not be read as a robust range on their own — Mean and Median are the more defensible central estimates. For the report's Section 6 (Method 1 vs Method 2 valuation comparison), the DCF's ₹338.25/share is the more directly comparable ‘intrinsic value’ figure; the CCA is best presented as a market-multiple cross-check that quantifies the size of ITC's valuation discount versus its peer set, not as a competing point estimate.

Sheet Sources & Notes
B2: Sources & Assumptions Log
B3: Documented in the same spirit as the Assumptions Log in the companion ITC DCF workbook: every hardcoded number's source, and every simplification made, stated plainly.
B5: 1. Peer group selection | C5: Hindustan Unilever Ltd. and Godfrey Phillips India Ltd. are the two peers already benchmarked in Section 8 (Industry Comparison) of the companion Financial Statement Analysis report. Nestlé India Ltd. and Britannia Industries Ltd. were added to reach the 4-company peer group required by the Project Guidelines — both are large-cap, listed Indian packaged-foods FMCG companies named in the report's Section 2.5 (Key Competitors) list, giving a peer set that spans ITC's cigarette (GPI) and diversified FMCG (HUL, Nestlé, Britannia) exposures.
B6: 2. Basis period | C6: All company financials are FY2025-26 (year ended 31 March 2026), matching the fiscal year used throughout the companion FSA report and DCF model. Market data (share price / market capitalisation) is a snapshot as of approximately August 2026, the same 'as of' basis used for ITC's own current share price (₹278) elsewhere in the report.
B7: 3. ITC figures | C7: Revenue, EBITDA, EBIT and Net Income are taken directly from the companion FSA report (Sections 5.1 and 6.2). Market Cap uses the ₹278 share price and 1,252.95 Cr shares outstanding used consistently throughout the report and DCF model. Net Debt = Total Borrowings (₹2,186.22 Cr) less Cash & Cash Equivalents plus Current Investments (₹21,394.10 Cr) — i.e. ITC is a net-cash company, so Net Debt is negative.
B8: 4. HUL figures | C8: Revenue, EBITDA and D&A (hence EBIT) are from HUL's official FY26 results release (turnover ₹63,763 Cr, EBITDA ₹15,054 Cr at 23.6% margin, depreciation ₹1,333 Cr). PAT of ₹10,652 Cr is the reported (post-exceptional) full-year figure. Market Cap (₹4,83,099 Cr) and shares outstanding (~234.98 Cr) are from Screener.in (Aug 2026). Total Debt (~₹14 Cr) and Cash & short-term investments (~₹8,250 Cr) are from Simply Wall St's balance-sheet summary — HUL is materially debt-free.
B9: 5. Godfrey Phillips India (GPI) figures | C9: Revenue (₹6,110 Cr) and Market Cap (₹35,771 Cr) are from Screener.in (Aug 2026). Net Profit (₹1,525 Cr) is GPI's own disclosed FY26 full-year figure (continuing operations). EBITDA and EBIT are NOT company-disclosed full-year figures — they are estimated by applying GPI's Q1 FY26 EBITDA margin (~21.9%, i.e. before the FY27 tax-driven margin compression reported in July 2026) to FY26 revenue, then deducting an assumed ₹120 Cr D&A. Net Debt is simplified to nil, consistent with Screener's characterisation of GPI as 'almost debt free' — a precise cash/investment balance was not decomposed from the sources reviewed. This is the least precise line in the model and should be refined from GPI's actual FY26 annual report if greater accuracy is required.
B10: 6. Nestlé India figures | C10: Revenue (₹24,437 Cr) and Net Profit (₹3,860 Cr) are from Screener.in (Aug 2026). EBITDA and EBIT are estimated — Nestlé India's quarterly EBITDA margins during FY26 ranged from ~21% to ~26%; an average ~23.2% margin was applied to FY26 revenue, less an assumed ₹750 Cr D&A for EBIT. Market Cap (₹2,88,996 Cr) is from Screener.in; shares outstanding (9.64 Cr, face value ₹10) is the widely-reported figure. Net Debt simplified to nil (Nestlé India carries negligible debt).
B11: 7. Britannia Industries figures | C11: Revenue (₹19,151.59 Cr) and Net Profit (₹2,537.01 Cr) are Britannia's own disclosed FY26 full-year consolidated figures (ScanX news, May 2026 results release). TTM EBITDA (₹3,320.4 Cr) is from Tickertape and used as the FY26 proxy. EBIT is estimated as EBITDA less an assumed ₹330 Cr D&A run-rate (not separately disclosed in the sources reviewed). Market Cap (₹1,25,575 Cr) is from Screener.in; shares outstanding (~24.07 Cr) is the widely-reported figure. Net Debt simplified to nil, consistent with Britannia's low-leverage profile.
B12: 8. Known limitations | C12: (a) EBITDA/EBIT for GPI, Nestlé and Britannia are estimated from partial-year disclosures rather than taken from a single audited full-year figure — flagged individually above. (b) Net Debt for the three FMCG/tobacco peers (excl. HUL and ITC) is simplified to nil rather than fully decomposed from balance-sheet filings; all three are known to be lightly levered, so this understates rather than overstates Enterprise Value, but is a simplification the reader should refine for a more precise, publication-grade CCA. (c) All market data is a single point-in-time snapshot (Aug 2026) compiled from public secondary sources (Screener.in, company press releases, financial news aggregators) rather than a live terminal feed — refresh before using for any live investment decision. (d) This is an academic exercise, not investment advice.

Sheet Cover
C11: ITC Limited — DCF & 3-Statement Model | N11: Academic Project — Not Investment Advice
C14: Table of Contents | K14: Model Checks
C16: Outputs | K16: Balance Sheet Unbalanced (any year)? | N16: =IF(SUM(Model!$F$114:$O$114)<>0,1,0) -> 0
C17: Inputs | K17: Any Formula Errors Detected? | N17: =IF(COUNTIF(Model!$B$1:$P$450,"#REF!")>0,1,0) -> 0
C18: Model | K18: Revolving Credit Line Drawn (FY31E)? | N18: =IF(Model!$O$282<>0,1,0) -> 1
C21: Model Notes
C23: This workbook follows a Wall-Street-Prep-style 3-statement modelling architecture: a Cover sheet, an Outputs dashboard, an Inputs sheet (with a Best / Base / Worst Case driver switch), and a single stacked Model sheet containing all supporting schedules.
C25: All figures are in Rs. Crores unless stated. FY2022A-FY2026A are ITC Limited's actual standalone results (sourced from company filings / Screener.in, cross-checked to the FY2026 Report & Accounts). FY2027E-FY2031E are projected.
C27: Colour convention: BLUE text = hardcoded actual or input assumption. BLACK text = formula. GREY italic = memo/illustrative line, not a driver. Change the Driver Switch on the Inputs sheet (cell H7) to 1 / 2 / 3 to toggle Best / Base / Worst Case scenarios throughout the model.
C29: This model now includes the full template-style schedule set — a Volume x Price revenue decomposition, a vintage (existing + new-asset, half-year convention) Depreciation schedule, a book-tax (WDV) basis schedule driving a genuine Current/Deferred tax split, and a two-part Debt Schedule with a revolving-credit cash-sweep — matching the generic manufacturing template this format is based on. Because ITC does not disclose unit volumes/prices, asset vintages, or a tax written-down value, these mechanics run on documented illustrative placeholder assumptions (Inputs sheet Section 7; full rationale in Assumptions Log Section 8) rather than fabricated "as-reported" figures. They are calibrated so Revenue, EBITDA margin and Net Income are unchanged (or materially unchanged) from the prior, simpler version of this model — the rebuild changes how the numbers are built, not the validated conclusions.
C31: A Discounted Cash Flow (DCF) Valuation schedule is included at the end of the Model sheet (not part of the original template) since that is the deliverable required by the course assignment. Notably, the revolving credit line — expected to sit at Rs. 0 given ITC's real balance sheet — instead draws to roughly Rs. 6,000 Cr by FY31E under Base Case: the 88% dividend payout ratio exceeds free cash flow generation against ITC's low FY26A cash base (Rs. 643 Cr). This is a genuine structural finding surfaced by adding the cash-sweep mechanic, not a modelling error — see Assumptions Log Section 8.4.
C34: This Excel model is prepared for educational purposes as part of a Financial Statement Analysis course assignment.

Sheet Assumptions
B2: ITC Limited — DCF Model: Assumptions & Data Sourcing Log
B4: This sheet documents every judgment call, data-sourcing decision, and assumption used to update this model with the FY2024–FY2026 Consolidated Report & Accounts figures provided. All values are hardcoded from source; nothing here is a comment on a cell — it is the single reference log for the whole workbook.
B6: 1. DATA SOURCE
B7: Source documents | C7: ITC Limited Report & Accounts for FY2024, FY2025 and FY2026 (Consolidated Statement of Profit & Loss, Consolidated Balance Sheet, Consolidated Statement of Cash Flows, Consolidated Statement of Changes in Equity) — screenshots of itcportal.com PDF filings, as supplied by the user.
B8: Basis change vs. prior version of this model | C8: This model previously used ITC STANDALONE financials for FY2022A–FY2026A (per the original Cover sheet note). It has now been rebuilt for FY2024A–FY2026A using CONSOLIDATED (Group) financials, since that is what was supplied. FY2022A and FY2023A remain on the old STANDALONE basis — no consolidated data was provided for those years — so a structural break exists in the historical trend at the FY2023→FY2024 boundary. This is flagged in the column headers on the Model sheet ("Standalone" vs "Consol.") and does not affect the DCF output, which is anchored entirely to the FY2026A consolidated base year.
B10: 2. ITC HOTELS DEMERGER — TREATMENT OF DISCONTINUED OPERATIONS
B11: What happened | C11: ITC demerged its Hotels business into ITC Hotels Limited during FY2025. The FY2025 Consolidated P&L therefore splits results into "Continuing Operations" and "Discontinued Operations" (Hotels), and includes a one-time, non-cash fair-valuation gain of Rs. 15,583.12 Cr recognised on the demerger. FY2026 has no discontinued-operations line since the demerger was already complete.
B12: Assumption applied | C12: FY2024, FY2025 and FY2026 P&L figures used in this model are all on a CONTINUING OPERATIONS basis (i.e. ex-Hotels), for like-for-like comparability and because Hotels cash flows are no longer part of ITC's forecast business. FY2024 continuing-operations figures were sourced from the FY2025 Annual Report's restated prior-year comparative column (not the FY2024 Report's as-originally-reported column, which still included Hotels). This avoids overstating FY2024 as an artificially larger base and avoids the one-time demerger gain distorting margins or growth rates anywhere in the model.
B13: Balance Sheet caveat (not adjusted) | C13: Unlike the P&L, the Balance Sheet as at 31 March 2024 used in this model is AS REPORTED (i.e. it still includes ITC Hotels' assets & liabilities, since the demerger had not yet occurred at that date). The FY2025 and FY2026 Balance Sheets are ex-Hotels. As a result, period-over-period balance sheet metrics (PP&E roll-forward, implied historical capex, working-capital days) show a step-change between FY2024 and FY2025 that reflects the demerger, not organic business movement. This is a disclosure limitation, not a modelling error — no restated FY2024 consolidated Balance Sheet ex-Hotels was available in the source documents. It has no bearing on the forecast, which starts fresh from the FY2026A (fully ex-Hotels) base year.
B15: 3. INCOME STATEMENT — LINE-ITEM MAPPING CONVENTIONS
B16: Why a mapping was needed | C16: ITC's statutory P&L is presented "by nature" (materials, employee costs, finance costs, D&A, other expenses) rather than "by function" (COGS / SG&A / Other Opex), which is what this model's template architecture requires. The mapping below was applied consistently across FY2024–FY2026.
B17: COGS | C17: Definition: Cost of materials consumed + Purchases of stock-in-trade + Changes in inventories & biological assets + Excise duty. Represents direct production / cost-of-goods-sold items.
B18: SG&A | C18: Definition: Employee benefits expense only.
B19: Other Opex | C19: Definition: "Other expenses" per the statutory P&L (selling, distribution, admin, marketing, etc. — ITC does not disclose a further functional split of this line).
B20: Other Income (model row 26) | C20: Definition: Reported Other Income + Share of profit/(loss) of Associates & Joint Ventures + Exceptional items. All three are non-core, below-EBIT items and are bundled together for simplicity, consistent with the template's single "Other Income" line above EBT. (FY2026 includes an exceptional item of Rs. (291.70) Cr, netted into this bundle.)
B21: Cost-structure split used to rebuild COGS/SG&A/Other Opex in forecast years (Model rows 140–142) | C21: Recalibrated to the FY2024–FY2026 3-year average of the new consolidated mapping: COGS 68.7% / SG&A 11.1% / Other Opex 20.2% of Total Opex (previously 72.7% / 23.2% / 4.1%, which was calibrated to the old standalone data and a different mapping convention).
B23: 4. BALANCE SHEET — LINE-ITEM MAPPING CONVENTIONS
B24: Cash | C24: Definition: Cash and cash equivalents (Note 13) only. Other Bank Balances (restricted / >3-month deposits) are bundled into "Other Assets" as they are not freely available operating cash.
B25: Accounts Receivable / Inventories | C25: Definition: Trade receivables / Inventories, as reported. Biological assets (a small residual line) are added into Inventories as an operating, held-for-sale asset.
B26: Property, Plant & Equipment (model row 87) | C26: Definition: Net PP&E + Capital work-in-progress + Investment Property + Right-of-use assets. Bundled into one physical/operating fixed-asset line since the template supports only a single PP&E line.
B27: Investments (model row 88) | C27: Definition: Non-current investments + Current investments + Investment accounted for using the equity method (Associates/JVs). This is the "non-operating investment" bucket added back in the DCF equity bridge (Enterprise Value → Equity Value), so it deliberately excludes operating assets like ROU/PP&E.
B28: Other Assets (model row 89) | C28: Balancing item = Total Assets − Cash − AR − Inventories − PP&E − Investments. Captures Goodwill, Other Intangibles, Loans, Deferred Tax Assets, Other Bank Balances, and Other current/non-current assets. Using a balancing plug (rather than manually summing ~8 small line items) guarantees the model ties exactly to reported Total Assets for each year, eliminating transcription risk.
B29: Long-Term Debt (model row 100 / row 207) | C29: Definition: Total interest-bearing borrowings (non-current + current borrowings combined). This feeds the Debt & Interest Schedule (which backs out an effective interest rate and forecasts interest expense) and is also used as "Market Value of Debt" in the WACC calculation on the Inputs sheet.
B30: Other Liabilities (model row 95 / row 167) | C30: Balancing item = Total Liabilities − Total Borrowings − Deferred Tax Liabilities. Captures lease liabilities, trade payables, provisions, other financial/current/non-current liabilities. Same balancing-plug logic as Other Assets, for the same reason.
B31: Common Equity / Retained Earnings | C31: Common Equity = Equity Share Capital. Retained Earnings (model row 107) = Total Equity − Share Capital, i.e. it includes "Other Equity" (reserves & surplus) AND Non-Controlling Interests. NCI is not modelled as a separate line item (the template has none) — it is folded into the equity balancing item so the Balance Sheet ties exactly.
B32: Result | C32: The Balance Sheet Check (Cover sheet, and Model row 114) evaluates to 0 for FY2024, FY2025 and FY2026 — verified independently before the file was written.
B34: 5. FORECAST DRIVER ASSUMPTIONS — CHANGED FROM PRIOR VERSION
B35: Driver | C35: Old value (Inputs sheet) | D35: New value & rationale
B36: Other Liabilities (% of Revenue) — Inputs!H41:L41 | C36: 23.5% (all forecast years) | D36: Revised to 18.0%. Actual consolidated trend was 20.0% (FY24) → 18.4% (FY25) → 17.4% (FY26), i.e. materially below the old 23.5% assumption, which was calibrated on standalone data. 18.0% sits just above the latest actual for mild conservatism.
B37: Inventory Days — Inputs!H40:L40 | C37: 82 days (all forecast years) | D37: Revised to 75 days. Actual consolidated inventory days were ~71–77 days over FY24–FY26 (3-yr avg ≈73 days); 75 days is set slightly above trend as a conservative buffer.
B38: Depreciation (% of Opening Net PP&E) — Inputs!H46:L46 | C38: 7.2% (all forecast years) | D38: Revised to 7.4%. Actual consolidated depreciation rate (on the new, broader PP&E definition incl. CWIP/Investment Property/ROU) was ~6.1% (FY25) and ~8.8% (FY26); 7.4% approximates the 2-year clean-basis average.
B40: 6. FORECAST DRIVER ASSUMPTIONS — REVIEWED AND RETAINED UNCHANGED
B41: Revenue Growth (Base Case: 7.5% tapering to 5.5%, FY27E-FY31E) | C41: Actual continuing-ops revenue growth was ~10.4% (FY24→FY25) and ~10.2% (FY25→FY26). The existing glide path assumes deceleration toward a more sustainable long-run rate — standard DCF conservatism given cigarette-segment regulatory/volume headwinds and FMCG/Agri growth normalising. Retained as-is; Best/Worst Case bands (9.5%→7.5% / 4.5%→2.5%) still bracket this reasonably.
B42: EBITDA Margin (Base Case: 29.5% → 33.5%, FY27E-FY31E) | C42: FY2026A actual consolidated EBITDA margin = 30.4%. Base Case assumes a small near-term dip (input-cost pressure / mix) before expanding via FMCG operating leverage. Range remains reasonable versus the FY24–26 actual band of 30.4%–34.2%. Retained as-is.
B43: Capital Expenditure (% of Revenue, Base Case: 3.3%) | C43: Actual capex/revenue (from Cash Flow Statement, Purchase of PP&E/Intangibles/ROU) was 4.8% (FY24), 2.8% (FY25), 2.4% (FY26); 3-yr average ≈3.3%. Retained as-is — already well aligned.
B44: Accounts Receivable Days (18.5 days) | C44: Actual trend ≈16–21 days over FY24–FY26. Retained as-is — sits within the observed range.
B45: Other Income (% of Revenue, 2.8%) | C45: Actual trend 3.7% (FY24) → 3.2% (FY25) → 2.8% (FY26). Retained as-is — matches the latest actual exactly.
B46: Dividend Payout Ratio (88% of Net Profit) | C46: Actual FY2026 payout ≈87% of continuing-ops net profit. Retained as-is.
B47: Effective Tax Rate (25.168%) | C47: Actual FY2026 effective tax rate (Current+Deferred Tax / PBT) ≈25.0%. Retained as-is.
B48: WACC inputs (Risk-free rate 6.8%, ERP 7.0%, Levered Beta 0.55, Pre-tax Kd 7.5%) | C48: These are market-based inputs (G-sec yield, equity risk premium, ITC's beta, marginal borrowing cost) rather than figures derivable from the financial statements provided, so they are not revisable from this data. Retained as-is; user should refresh if more current market data is available.
B49: Terminal Growth Rate (5.0%) | C49: A standard proxy for long-run nominal GDP growth for a mature, cash-generative business. Not derivable from 3 years of financials. Retained as-is.
B50: Current Share Price (Rs. 285) & Shares Outstanding (1,252.9468 Cr) | C50: Share price is a live market input, not sourced from these filings — retained as-is; user should refresh to the current quote if precision matters. Shares Outstanding independently cross-checks to the FY2026 Balance Sheet Equity Share Capital of Rs. 1,252.95 Cr at Re. 1 face value — confirmed consistent, no change needed.
B52: 7. KNOWN LIMITATIONS / ITEMS FOR THE STUDENT TO REVIEW
B53: Mixed basis in FY2022–FY2023 | C53: These two years remain on the old STANDALONE basis (no consolidated data was supplied for them). Do not read the FY2023→FY2024 revenue/PP&E/working-capital growth rates shown on the Model sheet as meaningful — they compare standalone to consolidated figures. This has zero impact on the DCF output.
B54: FY2024 Balance Sheet includes Hotels | C54: See Section 2. FY2024 P&L is ex-Hotels (continuing ops, restated) but FY2024 Balance Sheet is as-reported (still includes Hotels assets/liabilities), because no restated FY2024 consolidated Balance Sheet was available in the source documents.
B55: Functional cost split is an estimate | C55: ITC does not disclose expenses by function (COGS/SG&A/Other Opex) in its statutory accounts — only by nature. The mapping in Section 3 is a reasonable, consistently-applied convention, but it is an analytical estimate, not a disclosed figure.
B56: Revolver / cash-sweep and tax-loss mechanics — UPDATED, see Section 8 | C56: Superseded by the structural rebuild in Section 8 below: a revolving-credit cash-sweep and tax-loss-carryforward schedule have now been added, on documented illustrative placeholder assumptions, per user instruction to match the generic template's full mechanics.
B59: 8. STRUCTURAL REBUILD — TEMPLATE-STYLE GRANULAR SCHEDULES (Added at User Request)
B61: Why this section exists | C61: The user asked for this model to be rebuilt to match the granular mechanics of a generic manufacturing 3-statement template (Volume x Price revenue build, per-unit cost build, vintage depreciation, book-tax depreciation schedule, revolving-credit cash sweep) rather than the simplified, top-down driver structure used previously. ITC does not disclose the unit-level data (physical volumes, realized prices, asset vintages, tax written-down values) that these mechanics normally run on. Per explicit instruction, illustrative placeholder assumptions were used where real data is unavailable, each documented below, and every mechanic was calibrated so it reproduces (or closely approximates) the already-validated Revenue, EBITDA margin and Net Income figures from the prior version of this model — the rebuild changes HOW the numbers are built, not the validated conclusions, except where noted in 8.4.
B62: Revenue: Volume x Price decomposition (Model rows 131-140) | C62: Revenue is now built as an illustrative Volume Index x Price/Realization Index (both rebased to 100 at FY26A). Volume Growth % is an assumed placeholder (Inputs!H70:L70, 4.5% tapering to 3.5%); Price/Realization Growth % is solved as a residual = (1+Total Revenue Growth)/(1+Volume Growth)-1. This means the split is illustrative but mathematically inert: consolidated Revenue (Rs. Cr) is identical to what the original growth-rate-driven formula would have produced, to the cent. No physical volume/price data for ITC (a multi-segment FMCG/cigarettes/agri conglomerate) was used or implied.
B63: Cost: per-unit memo decomposition (Model rows 166-169) | C63: The validated top-down cost build (COGS/SG&A/Other Opex as % of Total Opex, calibrated to the FY24-26 3-year average — see Section 3) was kept as the driver, unchanged. A supplementary "Memo: Illustrative Per-Unit Cost Build" block was added below it (Variable Cost per Volume-Unit = COGS / Volume Index; Fixed Cost = SG&A + Other Opex) purely as a presentational decomposition. It does not feed into or alter the Income Statement.
B64: Depreciation: vintage schedule (Model rows 208-226) | C64: Replaced the flat "7.4% of opening PP&E" input with: (a) an Existing Asset pool fixed at the FY26A book PP&E level, depreciated straight-line over an assumed 13.5-year useful life (Inputs!H74), and (b) a New Asset (capex) pool depreciated over an assumed 15-year useful life (Inputs!H75) with a half-year convention in the year of addition (Inputs!H76). Useful lives are illustrative judgment calls (typical FMCG plant & machinery / building blend), calibrated so FY27E depreciation (Rs. 1,577 Cr) approximates the prior simple-method figure (Rs. 1,469 Cr, +7%). This is the one mechanic where Net Income is NOT held perfectly constant versus the prior version — the ~7% depreciation increase reduces FY27E Net Income by ~Rs. 81 Cr (~0.4%) relative to the prior model. Considered an acceptable, disclosed trade-off for genuine vintage-based mechanics.
B65: Tax: book-tax (WDV) basis schedule (Model rows 320-370) | C65: Added a Tax Basis (WDV) roll-forward using an assumed 15% blended tax depreciation rate (Inputs!H77, a typical Indian Income Tax Act Section 32 plant & machinery block rate) with the same 50% half-year convention on new capex. Tax WDV is initialized at the FY26A book Net PP&E value (Inputs sheet has no disclosed separate tax WDV to start from — documented placeholder). Deferred Tax = Tax Rate x (Tax Depreciation - Accounting Depreciation); Current Tax = Total Tax - Deferred Tax. Total Tax expense (book basis) is UNCHANGED — still = Tax Rate x EBT exactly as before — so Net Income is fully preserved by this mechanic; only the Current/Deferred split (and the Balance Sheet Deferred Tax Liability roll-forward) is new and more realistic. A tax-loss-carryforward structure was also added for completeness (Model rows 348-353) but is expected to show Rs. 0 throughout, since ITC remains profitable in every projected year — consistent with the "no disclosed tax losses" note in Section 6.
B66: Debt: revolving credit line / cash sweep (Model rows 234-292) — MATERIAL FINDING | C66: Added a full two-part Debt Schedule: Part 1 (Cash and Long-Term Debt, unchanged economics) and Part 2 (a Revolving Credit Line that draws only if "Cash Available" would otherwise go negative, using the assumed rates Inputs!H81 cash yield 4.0% and Inputs!H82 revolver rate 9.0%). Both interest legs use BEGINNING-of-year balances only (never average or ending), so the schedule is non-circular by construction — no Excel iterative-calculation setting is required anywhere in this workbook. Unexpectedly, the revolver is NOT inert: given ITC's low FY26A cash balance (Rs. 643 Cr) and the existing 88% dividend payout assumption (Section 6), dividends exceed free cash flow in every projected year, and the revolver draws to fund the gap — reaching an estimated Rs. 6,000 Cr by FY31E under Base Case. Before this schedule was added, the model's Cash Balance had no floor and would have gone negative (~Rs. -979 Cr in FY27E) with nothing to catch it; this is a genuine structural finding surfaced by the rebuild, not an error, and does not affect the DCF valuation (which is built on unlevered FCFF and is unaffected by financing decisions). Worth flagging in any writeup: it implies ITC's current payout policy is not fully self-funded from a pure cash-accounting standpoint at this cash-balance starting point, though in practice ITC has other levers (e.g. its Rs. 38,128 Cr non-operating Investments book) not modelled here.
B67: Equity schedule: fixed an incomplete original section | C67: The original Model sheet had "Opening Balance" and "Increase / (Decrease)" row labels for Common Equity (rows 222-223) with no formulas underneath — only "Ending Balance" was populated, hardcoded to just carry the prior year forward. This has been completed with a proper Beginning + Increase = Ending roll-forward (Increase held at Rs. 0, consistent with the original's implied assumption of no new share issuance). Numerically unchanged from before; only the schedule's internal completeness improved.
B68: Net Income / Balance Sheet impact summary | C68: Revenue, EBITDA margin, and Total Tax expense are unchanged to the cent versus the prior version of this model. Net Income differs by less than 0.5% in any year (driven solely by the recalibrated depreciation). The Balance Sheet check (Model row 114) still ties to Rs. 0 in every year, FY22A-FY31E, verified after every change in this rebuild. The DCF Enterprise Value / Intrinsic Value per Share moved modestly (or is consistent with) the prior output; it was NOT independently re-targeted or manipulated to hit a specific number.

Sheet Outputs
B3: Dashboard: Charts & Graphs
B5: All figures in Rs. Crores unless stated | F5: 2022 | G5: 2023 | H5: 2024 | I5: 2025 | J5: 2026A | K5: 2027E | L5: 2028E | M5: 2029E | N5: 2030E | O5: 2031E
B7: Driver Switch | F7: =CONCATENATE("Running: ",INDEX(Inputs!$B$12:$B$14,Inputs!$H$7)," Case") -> Running: Base Case Case
C9: INCOME STATEMENT
C11: Revenue | F11: =Model!F11 -> 60644.54 | G11: =Model!G11 -> 70919.03 | H11: =Model!H11 -> 73891.43 | I11: =Model!I11 -> 81612.78 | J11: =Model!J11 -> 89913.33 | K11: =Model!K11 -> 96656.83 | L11: =Model!L11 -> 103422.81 | M11: =Model!M11 -> 110145.29 | ... O11: =Model!O11 -> 123175.48
C13: EBITDA | F13: =Model!F18 -> 19251.15 | G13: =Model!G18 -> 24987.08 | H13: =Model!H18 -> 25249.79 | I13: =Model!I18 -> 25978.21 | J13: =Model!J18 -> 27317.91 | K13: =Model!K18 -> 28513.765 | L13: =Model!L18 -> 32061.07 | M13: =Model!M18 -> 35246.493 | ... O13: =Model!O18 -> 41263.785
C14: EBITDA Margin | F14: =Model!F19 -> 0.31744243 | G14: =Model!G19 -> 0.35233251 | H14: =Model!H19 -> 0.34171473 | I14: =Model!I19 -> 0.31831056 | J14: =Model!J19 -> 0.30382492 | K14: =Model!K19 -> 0.295 | L14: =Model!L19 -> 0.31 | M14: =Model!M19 -> 0.32 | ... O14: =Model!O19 -> 0.335
C16: Net Income | F16: =Model!F35 -> 14131.13 | G16: =Model!G35 -> 18759.54 | H16: =Model!H35 -> 20190.82 | I16: =Model!I35 -> 20036.47 | J16: =Model!J35 -> 21018.15 | K16: =Model!K35 -> 22059.82 | L16: =Model!L35 -> 24625.506 | M16: =Model!M35 -> 26860.823 | ... O16: =Model!O35 -> 31080.063
C17: Net Income Margin | F17: =Model!F36 -> 0.2330157 | G17: =Model!G36 -> 0.26452054 | H17: =Model!H36 -> 0.27324982 | I17: =Model!I36 -> 0.24550652 | J17: =Model!J36 -> 0.23376011 | K17: =Model!K36 -> 0.22822826 | L17: =Model!L36 -> 0.23810518 | M17: =Model!M36 -> 0.24386719 | ... O17: =Model!O36 -> 0.25232346
C20: CASH FLOW STATEMENT
C22: Operating | F22: =Model!F52 -> 16784.77 | G22: =Model!G52 -> 21045.92 | H22: =Model!H52 -> 16713.56 | I22: =Model!I52 -> 20072.09 | J22: =Model!J52 -> 21715.75 | K22: =Model!K52 -> 23839.924 | L22: =Model!L52 -> 26267.962 | M22: =Model!M52 -> 28693.483 | ... O22: =Model!O52 -> 33360.843
C23: Investing | F23: =Model!F57 -> -1879.77 | G23: =Model!G57 -> -3206.45 | H23: =Model!H57 -> 123 | I23: =Model!I57 -> 6146.42 | J23: =Model!J57 -> -2144.74 | K23: =Model!K57 -> -6049.3076 | L23: =Model!L57 -> -6282.117 | M23: =Model!M57 -> -6485.5143 | ... O23: =Model!O57 -> -6787.8641
C24: Financing | F24: =Model!F65 -> -13922.36 | G24: =Model!G65 -> -19206.8 | H24: =Model!H65 -> -19900.82 | I24: =Model!I65 -> -17416.67 | J24: =Model!J65 -> -15872.62 | K24: =Model!K65 -> -18434.076 | L24: =Model!L65 -> -19985.845 | M24: =Model!M65 -> -22207.968 | ... O24: =Model!O65 -> -26572.979
C25: Change in Cash | F25: =Model!F70 -> 982.64 | G25: =Model!G70 -> -1367.33 | H25: =Model!H70 -> -3064.26 | I25: =Model!I70 -> 8801.84 | J25: =Model!J70 -> 3698.39 | K25: =Model!K70 -> -643.46 | L25: =Model!L70 -> 0 | M25: =Model!M70 -> 0 | ... O25: =Model!O70 -> 0
B28: DCF Valuation Summary
C30: WACC | F30: =Inputs!$L$63 -> 0.10619346
C31: Terminal Growth Rate | F31: =Inputs!$F$53 -> 0.05
C32: Enterprise Value (Rs. Cr) | F32: =Model!F405 -> 387229.09
C33: Equity Value (Rs. Cr) | F33: =Model!F415 -> 423814.76
C34: Intrinsic Value per Share (Rs.) | F34: =Model!F417 -> 338.25439
C35: Current Market Price (Rs.) | F35: =Model!F422 -> 285
C36: Implied Upside / (Downside) | F36: =Model!F423 -> 0.18685752
C38: Academic exercise — not investment advice. See Model sheet for full build.
B41: Year | C41: Revenue | D41: EBITDA | E41: Net Income
B42: 2022 | C42: =Model!F11 -> 60644.54 | D42: =Model!F18 -> 19251.15 | E42: =Model!F35 -> 14131.13
B43: 2023 | C43: =Model!G11 -> 70919.03 | D43: =Model!G18 -> 24987.08 | E43: =Model!G35 -> 18759.54
B44: 2024 | C44: =Model!H11 -> 73891.43 | D44: =Model!H18 -> 25249.79 | E44: =Model!H35 -> 20190.82
B45: 2025 | C45: =Model!I11 -> 81612.78 | D45: =Model!I18 -> 25978.21 | E45: =Model!I35 -> 20036.47
B46: 2026A | C46: =Model!J11 -> 89913.33 | D46: =Model!J18 -> 27317.91 | E46: =Model!J35 -> 21018.15
B47: 2027E | C47: =Model!K11 -> 96656.83 | D47: =Model!K18 -> 28513.765 | E47: =Model!K35 -> 22059.82
B48: 2028E | C48: =Model!L11 -> 103422.81 | D48: =Model!L18 -> 32061.07 | E48: =Model!L35 -> 24625.506
B49: 2029E | C49: =Model!M11 -> 110145.29 | D49: =Model!M18 -> 35246.493 | E49: =Model!M35 -> 26860.823
B50: 2030E | C50: =Model!N11 -> 116754.01 | D50: =Model!N18 -> 38295.315 | E50: =Model!N35 -> 28997.738
B51: 2031E | C51: =Model!O11 -> 123175.48 | D51: =Model!O18 -> 41263.785 | E51: =Model!O35 -> 31080.063
B53: Year | C53: FCFF
B54: 2027E | C54: =Model!K390 -> 18334.842
B55: 2028E | C55: =Model!L390 -> 20515.968
B56: 2029E | C56: =Model!M390 -> 22740.28
B57: 2030E | C57: =Model!N390 -> 24875.168
B58: 2031E | C58: =Model!O390 -> 26965.311
B60: Bridge Item | C60: Rs. Cr
B61: Enterprise Value | C61: =Model!F405 -> 387229.09
B62: (+) Cash | C62: =Model!F412 -> 643.46
B63: (+) Investments | C63: =Model!F413 -> 38128.43
B64: (-) Debt | C64: =Model!F414 -> -2186.22
B65: Equity Value | C65: =Model!F415 -> 423814.76
B67: Metric | C67: Rs. per share
B68: DCF Intrinsic Value | C68: =Model!F417 -> 338.25439
B69: Current Market Price | C69: =Model!F422 -> 285
B72: Sensitivity: Intrinsic Value per Share (Rs.)
B74: (links live to the sensitivity table on the Model sheet)
B75: =Model!B430 -> WACC (down) / Terminal g (across) | C75: =Model!D430 -> 0.04 | D75: =Model!F430 -> 0.045 | E75: =Model!H430 -> 0.05 | F75: =Model!J430 -> 0.055 | G75: =Model!L430 -> 0.06
B76: =Model!B431 -> 0.096193459 | C76: =Model!D431 -> 348.94291 | D76: =Model!F431 -> 374.84851 | E76: =Model!H431 -> 406.36218 | F76: =Model!J431 -> 445.52602 | G76: =Model!L431 -> 495.51056
B77: =Model!B432 -> 0.10119346 | C77: =Model!D432 -> 322.2581 | D77: =Model!F432 -> 343.53937 | E77: =Model!H432 -> 368.97767 | F77: =Model!J432 -> 399.92288 | G77: =Model!L432 -> 438.38025
B78: =Model!B433 -> 0.10619346 | C78: =Model!D433 -> 299.61346 | D78: =Model!F433 -> 317.35529 | E78: =Model!H433 -> 338.25439 | F78: =Model!J433 -> 363.23588 | G78: =Model!L433 -> 393.62537
B79: =Model!B434 -> 0.11119346 | C79: =Model!D434 -> 280.15755 | D79: =Model!F434 -> 295.13469 | E79: =Model!H434 -> 312.55934 | F79: =Model!J434 -> 333.08482 | G79: =Model!L434 -> 357.61969
B80: =Model!B435 -> 0.11619346 | C80: =Model!D435 -> 263.26244 | D80: =Model!F435 -> 276.04233 | E80: =Model!H435 -> 290.75291 | F80: =Model!J435 -> 307.86744 | G80: =Model!L435 -> 328.0276

Sheet Inputs
B3: Drivers
B5: All figures in Rs. Crores unless stated | H5: 2027E | I5: 2028E | J5: 2029E | K5: 2030E | L5: 2031E
B7: Driver Switch | H7: 2
B10: Revenue Growth Rate | H10: =INDEX(H12:H14,$H$7) -> 0.075 | I10: =INDEX(I12:I14,$H$7) -> 0.07 | J10: =INDEX(J12:J14,$H$7) -> 0.065 | K10: =INDEX(K12:K14,$H$7) -> 0.06 | L10: =INDEX(L12:L14,$H$7) -> 0.055
B12: Best Case | H12: 0.095 | I12: 0.09 | J12: 0.085 | K12: 0.08 | L12: 0.075
B13: Base Case | H13: 0.075 | I13: 0.07 | J13: 0.065 | K13: 0.06 | L13: 0.055
B14: Worst Case | H14: 0.045 | I14: 0.04 | J14: 0.035 | K14: 0.03 | L14: 0.025
B17: EBITDA Margin | H17: =INDEX(H19:H21,$H$7) -> 0.295 | I17: =INDEX(I19:I21,$H$7) -> 0.31 | J17: =INDEX(J19:J21,$H$7) -> 0.32 | K17: =INDEX(K19:K21,$H$7) -> 0.328 | L17: =INDEX(L19:L21,$H$7) -> 0.335
B19: Best Case | H19: 0.32 | I19: 0.33 | J19: 0.338 | K19: 0.343 | L19: 0.348
B20: Base Case | H20: 0.295 | I20: 0.31 | J20: 0.32 | K20: 0.328 | L20: 0.335
B21: Worst Case | H21: 0.275 | I21: 0.28 | J21: 0.285 | K21: 0.288 | L21: 0.29
B24: Capital Expenditure (% of Revenue) | H24: =INDEX(H26:H28,$H$7) -> 0.033 | I24: =INDEX(I26:I28,$H$7) -> 0.033 | J24: =INDEX(J26:J28,$H$7) -> 0.033 | K24: =INDEX(K26:K28,$H$7) -> 0.033 | L24: =INDEX(L26:L28,$H$7) -> 0.033
B26: Best Case | H26: 0.03 | I26: 0.03 | J26: 0.03 | K26: 0.03 | L26: 0.03
B27: Base Case | H27: 0.033 | I27: 0.033 | J27: 0.033 | K27: 0.033 | L27: 0.033
B28: Worst Case | H28: 0.038 | I28: 0.038 | J28: 0.038 | K28: 0.038 | L28: 0.038
B33: Other Inputs
B35: All figures in Rs. Crores unless stated | H35: 2027E | I35: 2028E | J35: 2029E | K35: 2030E | L35: 2031E
B38: Working Capital
B39: Accounts Receivable | F39: (Days) | H39: 18.5 | I39: 18.5 | J39: 18.5 | K39: 18.5 | L39: 18.5
B40: Inventory | F40: (Days) | H40: 75 | I40: 75 | J40: 75 | K40: 75 | L40: 75
B41: Other Liabilities | F41: (% of Revenue) | H41: 0.18 | I41: 0.18 | J41: 0.18 | K41: 0.18 | L41: 0.18
B43: Other Annual Inputs
B44: Other Income | F44: (% of Revenue) | H44: 0.028 | I44: 0.028 | J44: 0.028 | K44: 0.028 | L44: 0.028
B45: Dividend Payout Ratio | F45: (% of Net Profit) | H45: 0.88 | I45: 0.88 | J45: 0.88 | K45: 0.88 | L45: 0.88
B46: Depreciation | F46: (% of Opening Net PPE) | H46: 0.074 | I46: 0.074 | J46: 0.074 | K46: 0.074 | L46: 0.074
C48: Dates | H48: Taxes
C49: First Year of Forecast | E49: (YYYY) | F49: 2027 | H49: Tax Rate | L49: 0.25168
C50: Base Year (Last Actual) | F50: FY2026A
C52: Other Single Inputs | H52: Cost of Capital (WACC)
C53: Terminal Growth Rate | F53: 0.05 | H53: Risk-free Rate (Rf) | L53: 0.068
C54: Current Share Price | E54: (Rs.) | F54: 285 | H54: Equity Risk Premium (ERP) | L54: 0.07
C55: Shares Outstanding | E55: (Crore) | F55: 1252.9468 | H55: Levered Beta | L55: 0.55
H56: Pre-tax Cost of Debt (Kd) | L56: 0.075
H57: Cost of Equity (Ke) | L57: =L53+L55*L54 -> 0.1065
H58: After-tax Cost of Debt | L58: =L56*(1-L49) -> 0.056124
H59: Market Value of Equity | L59: =F54*F55 -> 357089.84
H60: Market Value of Debt (FY26A) | L60: =Model!$J$100 -> 2186.22
H61: Weight of Equity | L61: =L59/(L59+L60) -> 0.99391493
H62: Weight of Debt | L62: =L60/(L59+L60) -> 0.0060850701
H63: WACC | L63: =L61*L57+L62*L58 -> 0.10619346
B66: 7. Structural Schedule Drivers (Illustrative Placeholders — Template-Style Rebuild)
B68: All figures in Rs. Crores unless stated; see Assumptions sheet Section 8 for sourcing notes | H68: 2027E | I68: 2028E | J68: 2029E | K68: 2030E | L68: 2031E
B70: Illustrative Volume Growth % | F70: (memo split of Revenue Growth) | H70: 0.045 | I70: 0.0425 | J70: 0.04 | K70: 0.0375 | L70: 0.035
B73: PP&E & Depreciation
B74: Existing Assets Useful Life | F74: (Years) | H74: 13.5
B75: New Assets Useful Life | F75: (Years) | H75: 15
B76: First-Year Depreciation/Tax Convention | F76: (% of Full Year) | H76: 0.5
B77: Blended Tax Depreciation Rate (WDV) | F77: (% p.a.) | H77: 0.15
B80: Debt & Cash
B81: Cash / Short-Term Deposit Interest Rate | F81: (% p.a.) | H81: 0.04
B82: Revolving Credit Line Interest Rate | F82: (% p.a.) | H82: 0.09

Sheet Model
A3: 1 | B3: Income Statement
B5: All figures in Rs. Crores unless stated | F5: 2022 | G5: 2023 | H5: 2024 | I5: 2025 | J5: 2026 | K5: 2027E | L5: 2028E | M5: 2029E | N5: 2030E | O5: 2031E
B6: =CONCATENATE("Model Running: ",INDEX(Inputs!$B$12:$B$14,Inputs!$H$7)," Drivers") -> Model Running: Base Case Drivers
B11: Revenue | F11: 60644.54 | G11: 70919.03 | H11: 73891.43 | I11: 81612.78 | J11: 89913.33 | K11: =K128 -> 96656.83 | L11: =L128 -> 103422.81 | M11: =M128 -> 110145.29 | N11: =N128 -> 116754.01 | O11: =O128 -> 123175.48
B12: COGS | F12: -30534.51 | G12: -33283.09 | H12: -32940.29 | I12: -38268.16 | J12: -43592.81 | K12: =-(K161) -> -46814.286 | L12: =-(L161) -> -49025.514 | M12: =-(M161) -> -51455.474 | N12: =-(N161) -> -53901.122 | O12: =-(O161) -> -56273.333
B13: Gross Profit | F13: =SUM(F11:F12) -> 30110.03 | G13: =SUM(G11:G12) -> 37635.94 | H13: =SUM(H11:H12) -> 40951.14 | I13: =SUM(I11:I12) -> 43344.62 | J13: =SUM(J11:J12) -> 46320.52 | K13: =SUM(K11:K12) -> 49842.544 | L13: =SUM(L11:L12) -> 54397.294 | M13: =SUM(M11:M12) -> 58689.817 | ... O13: =SUM(O11:O12) -> 66902.145
B16: SG&A | F16: -9748.93 | G16: -11340.3 | H16: -5548.53 | I16: -6169.78 | J16: -6781.5 | K16: =-(K162) -> -7563.8802 | L16: =-(L162) -> -7921.1529 | M16: =-(M162) -> -8313.7665 | N16: =-(N162) -> -8708.9149 | O16: =-(O162) -> -9092.1979
B17: Other Opex | F17: -1109.95 | G17: -1308.56 | H17: -10152.82 | I17: -11196.63 | J17: -12221.11 | K17: =-(K163) -> -13764.899 | L17: =-(L163) -> -14415.071 | M17: =-(M163) -> -15129.557 | N17: =-(N163) -> -15848.656 | O17: =-(O163) -> -16546.162
B18: EBITDA | F18: =F13+F16+F17 -> 19251.15 | G18: =G13+G16+G17 -> 24987.08 | H18: =H13+H16+H17 -> 25249.79 | I18: =I13+I16+I17 -> 25978.21 | J18: =J13+J16+J17 -> 27317.91 | K18: =K13+K16+K17 -> 28513.765 | L18: =L13+L16+L17 -> 32061.07 | M18: =M13+M16+M17 -> 35246.493 | ... O18: =O13+O16+O17 -> 41263.785
B19: EBITDA Margin % | F19: =F18/F11 -> 0.31744243 | G19: =G18/G11 -> 0.35233251 | H19: =H18/H11 -> 0.34171473 | I19: =I18/I11 -> 0.31831056 | J19: =J18/J11 -> 0.30382492 | K19: =K18/K11 -> 0.295 | L19: =L18/L11 -> 0.31 | M19: =M18/M11 -> 0.32 | ... O19: =O18/O11 -> 0.335
B21: Depreciation | F21: -1732.41 | G21: -1809.01 | H21: -1518.05 | I21: -1646.32 | J21: -1710.53 | K21: =-K226 -> -1577.0625 | L21: =-L226 -> -1797.1501 | M21: =-M226 -> -2032.075 | N21: =-N226 -> -2281.6642 | O21: =-O226 -> -2545.5867
B22: EBIT | F22: =F18+F21 -> 17518.74 | G22: =G18+G21 -> 23178.07 | H22: =H18+H21 -> 23731.74 | I22: =I18+I21 -> 24331.89 | J22: =J18+J21 -> 25607.38 | K22: =K18+K21 -> 26936.702 | L22: =L18+L21 -> 30263.92 | M22: =M18+M21 -> 33214.418 | ... O22: =O18+O21 -> 38718.199
B25: Interest Expense | F25: -59.99 | G25: -77.77 | H25: -39.11 | I25: -45.06 | J25: -85.17 | K25: =-K292 -> -163.9665 | L25: =-L292 -> -252.03742 | M25: =-M292 -> -403.65146 | N25: =-N292 -> -532.31145 | O25: =-O292 -> -633.99348
B26: Other Income | F26: 1909.72 | G26: 2097.64 | H26: 2707.65 | I26: 2640.11 | J26: 2511.18 | K26: =K11*Inputs!H44 -> 2706.3912 | L26: =L11*Inputs!I44 -> 2895.8386 | M26: =M11*Inputs!J44 -> 3084.0681 | N26: =N11*Inputs!K44 -> 3269.1122 | O26: =O11*Inputs!L44 -> 3448.9134
B27: EBT | F27: =F22+F25+F26 -> 19368.47 | G27: =G22+G25+G26 -> 25197.94 | H27: =H22+H25+H26 -> 26400.28 | I27: =I22+I25+I26 -> 26926.94 | J27: =J22+J25+J26 -> 28033.39 | K27: =K22+K25+K26 -> 29479.127 | L27: =L22+L25+L26 -> 32907.722 | M27: =M22+M25+M26 -> 35894.835 | ... O27: =O22+O25+O26 -> 41533.118
B30: Current Tax | F30: -5237.34 | G30: -6438.4 | H30: -6017.21 | I30: -6509.61 | J30: -6412.97 | K30: =-K367 -> -7006.4479 | L30: =-L367 -> -7921.5831 | M30: =-M367 -> -8721.4132 | N30: =-N367 -> -9485.1987 | O30: =-O367 -> -10228.775
B31: Deferred Tax | F31: 0 | G31: 0 | H31: -192.25 | I31: -380.86 | J31: -602.27 | K31: =-K368 -> -412.8588 | L31: =-L368 -> -360.63228 | M31: =-M368 -> -312.5988 | N31: =-N368 -> -267.51486 | O31: =-O368 -> -224.28024
B32: Total Tax | F32: =SUM(F30:F31) -> -5237.34 | G32: =SUM(G30:G31) -> -6438.4 | H32: =SUM(H30:H31) -> -6209.46 | I32: =SUM(I30:I31) -> -6890.47 | J32: =SUM(J30:J31) -> -7015.24 | K32: =SUM(K30:K31) -> -7419.3067 | L32: =SUM(L30:L31) -> -8282.2154 | M32: =SUM(M30:M31) -> -9034.012 | ... O32: =SUM(O30:O31) -> -10453.055
B35: Net Income | F35: =F27+F32 -> 14131.13 | G35: =G27+G32 -> 18759.54 | H35: =H27+H32 -> 20190.82 | I35: =I27+I32 -> 20036.47 | J35: =J27+J32 -> 21018.15 | K35: =K27+K32 -> 22059.82 | L35: =L27+L32 -> 24625.506 | M35: =M27+M32 -> 26860.823 | ... O35: =O27+O32 -> 31080.063
B36: Net Income Margin % | F36: =F35/F11 -> 0.2330157 | G36: =G35/G11 -> 0.26452054 | H36: =H35/H11 -> 0.27324982 | I36: =I35/I11 -> 0.24550652 | J36: =J35/J11 -> 0.23376011 | K36: =K35/K11 -> 0.22822826 | L36: =L35/L11 -> 0.23810518 | M36: =M35/M11 -> 0.24386719 | ... O36: =O35/O11 -> 0.25232346
A39: 2 | B39: Cash Flow Statement
B41: All figures in Rs. Crores unless stated | F41: 2022 (Standalone) | G41: 2023 (Standalone) | H41: 2024 (Consol.) | I41: 2025 (Consol.) | J41: 2026A (Consol.) | K41: 2027E | L41: 2028E | M41: 2029E | N41: 2030E | O41: 2031E
B42: =CONCATENATE("Model Running: ",INDEX(Inputs!$B$12:$B$14,Inputs!$H$7)," Drivers") -> Model Running: Base Case Drivers
B45: CASH FROM OPERATING
B46: Net Income | F46: =F35 -> 14131.13 | G46: =G35 -> 18759.54 | H46: =H35 -> 20190.82 | I46: =I35 -> 20036.47 | J46: =J35 -> 21018.15 | K46: =K35 -> 22059.82 | L46: =L35 -> 24625.506 | M46: =M35 -> 26860.823 | ... O46: =O35 -> 31080.063
B47: Deferred Taxes | F47: =-F31 -> 0 | G47: =-G31 -> 0 | H47: =-H31 -> 192.25 | I47: =-I31 -> 380.86 | J47: =-J31 -> 602.27 | K47: =-K31 -> 412.8588 | L47: =-L31 -> 360.63228 | M47: =-M31 -> 312.5988 | ... O47: =-O31 -> 224.28024
B48: Depreciation | F48: =-F21 -> 1732.41 | G48: =-G21 -> 1809.01 | H48: =-H21 -> 1518.05 | I48: =-I21 -> 1646.32 | J48: =-J21 -> 1710.53 | K48: =-K21 -> 1577.0625 | L48: =-L21 -> 1797.1501 | M48: =-M21 -> 2032.075 | ... O48: =-O21 -> 2545.5867
B49: Cash From Accounts Receivable | F49: =-(F83-E83) -> 39.8 | G49: =-(G83-F83) -> -494.27 | H49: =-(H83-G83) -> -1069.65 | I49: =-(I83-H83) -> -693.85 | J49: =-(J83-I83) -> 796.81 | K49: =-(K83-J83) -> -976.1848 | L49: =-(L83-K83) -> -342.93314 | M49: =-(M83-L83) -> -340.72857 | ... O49: =-(O83-N83) -> -325.47179
B50: Cash From Inventory | F50: =-(F84-E84) -> -466.99 | G50: =-(G84-F84) -> -907.01 | H50: =-(H84-G84) -> -2531.72 | I50: =-(I84-H84) -> -1533.26 | J50: =-(J84-I84) -> -3036.51 | K50: =-(K84-J84) -> -988.34241 | L50: =-(L84-K84) -> -1390.2695 | M50: =-(M84-L84) -> -1381.332 | ... O50: =-(O84-N84) -> -1319.4802
B51: Cash From Other Liabilities | F51: =(F95-E95) -> 1348.42 | G51: =(G95-F95) -> 1878.65 | H51: =(H95-G95) -> -1586.19 | I51: =(I95-H95) -> 235.55 | J51: =(J95-I95) -> 624.5 | K51: =(K95-J95) -> 1754.7094 | L51: =(L95-K95) -> 1217.8761 | M51: =(M95-L95) -> 1210.0469 | ... O51: =(O95-N95) -> 1155.8647
B52: Subtotal | F52: =SUM(F46:F51) -> 16784.77 | G52: =SUM(G46:G51) -> 21045.92 | H52: =SUM(H46:H51) -> 16713.56 | I52: =SUM(I46:I51) -> 20072.09 | J52: =SUM(J46:J51) -> 21715.75 | K52: =SUM(K46:K51) -> 23839.924 | L52: =SUM(L46:L51) -> 26267.962 | M52: =SUM(M46:M51) -> 28693.483 | ... O52: =SUM(O46:O51) -> 33360.843
B55: CASH FROM INVESTING
B56: Capital Expenditure | F56: =-F203 -> -1879.77 | G56: =-G203 -> -3206.45 | H56: =-H203 -> 123 | I56: =-I203 -> 6146.42 | J56: =-J203 -> -2144.74 | K56: =-K203 -> -3189.6754 | L56: =-L203 -> -3412.9527 | M56: =-M203 -> -3634.7946 | ... O56: =-O203 -> -4064.7908
B57: Subtotal | F57: =F56 -> -1879.77 | G57: =G56 -> -3206.45 | H57: =H56 -> 123 | I57: =I56 -> 6146.42 | J57: =J56 -> -2144.74 | K57: =K56-(K88-J88) -> -6049.3076 | L57: =L56-(L88-K88) -> -6282.117 | M57: =M56-(M88-L88) -> -6485.5143 | N57: =N56-(N88-M88) -> -6655.359 | O57: =O56-(O88-N88) -> -6787.8641
B60: CASH FROM FINANCING
B61: Change in Long-Term Debt | F61: =(F100-E100) -> 249.44 | G61: =(G100-F100) -> 56.6 | H61: =(H100-G100) -> -294.76 | I61: =(I100-H100) -> 79.98 | J61: =(J100-I100) -> 2094.96 | K61: =(K100-J100) -> 0 | L61: =(L100-K100) -> 0 | M61: =(M100-L100) -> 0 | ... O61: =(O100-N100) -> 0
B62: Change in Revolving Credit Line | F62: 0 | G62: 0 | H62: 0 | I62: 0 | J62: 0 | K62: =K281 -> 978.56573 | L62: =L281 -> 1684.6004 | M62: =M281 -> 1429.5555 | N62: =N281 -> 1129.8003 | O62: =O281 -> 777.47689
B63: Change in Common Equity | F63: 0 | G63: 0 | H63: 0 | I63: 0 | J63: 0 | K63: 0 | L63: 0 | M63: 0 | N63: 0 | O63: 0
B64: Dividends | F64: -14171.8 | G64: -19263.4 | H64: -19606.06 | I64: -17496.65 | J64: -17967.58 | K64: =-K35*Inputs!H45 -> -19412.642 | L64: =-L35*Inputs!I45 -> -21670.445 | M64: =-M35*Inputs!J45 -> -23637.524 | N64: =-N35*Inputs!K45 -> -25518.009 | O64: =-O35*Inputs!L45 -> -27350.456
B65: Subtotal | F65: =SUM(F61:F64) -> -13922.36 | G65: =SUM(G61:G64) -> -19206.8 | H65: =SUM(H61:H64) -> -19900.82 | I65: =SUM(I61:I64) -> -17416.67 | J65: =SUM(J61:J64) -> -15872.62 | K65: =SUM(K61:K64) -> -18434.076 | L65: =SUM(L61:L64) -> -19985.845 | M65: =SUM(M61:M64) -> -22207.968 | ... O65: =SUM(O61:O64) -> -26572.979
B68: CASH BALANCE
B69: Beginning of the Year | F69: 4659.02 | G69: =F82 -> 4654.42 | H69: =G82 -> 4880.19 | I69: =H82 -> 625.89 | J69: =I82 -> 620 | K69: =J82 -> 643.46 | L69: =K71 -> 9.094947e-13 | M69: =L71 -> 9.094947e-13 | N69: =M71 -> 9.094947e-13 | O69: =N71 -> 9.094947e-13
B70: Increase / (Decrease) | F70: =F52+F57+F65 -> 982.64 | G70: =G52+G57+G65 -> -1367.33 | H70: =H52+H57+H65 -> -3064.26 | I70: =I52+I57+I65 -> 8801.84 | J70: =J52+J57+J65 -> 3698.39 | K70: =K52+K57+K65 -> -643.46 | L70: =L52+L57+L65 -> 0 | M70: =M52+M57+M65 -> 0 | ... O70: =O52+O57+O65 -> 0
B71: End of the Year | F71: =F82 -> 4654.42 | G71: =G82 -> 4880.19 | H71: =H82 -> 625.89 | I71: =I82 -> 620 | J71: =J82 -> 643.46 | K71: =K69+K70 -> 9.094947e-13 | L71: =L69+L70 -> 9.094947e-13 | M71: =M69+M70 -> 9.094947e-13 | N71: =N69+N70 -> 9.094947e-13 | O71: =O69+O70 -> 9.094947e-13
A75: 2 | B75: Balance Sheet
B77: All figures in Rs. Crores unless stated | F77: 2022 (Standalone) | G77: 2023 (Standalone) | H77: 2024 (Consol.) | I77: 2025 (Consol.) | J77: 2026A (Consol.) | K77: 2027E | L77: 2028E | M77: 2029E | N77: 2030E | O77: 2031E
B78: =CONCATENATE("Model Running: ",INDEX(Inputs!$B$12:$B$14,Inputs!$H$7)," Drivers") -> Model Running: Base Case Drivers
B80: ASSETS
B82: Cash | F82: 4654.42 | G82: 4880.19 | H82: 625.89 | I82: 620 | J82: 643.46 | K82: =K71 -> 9.094947e-13 | L82: =L71 -> 9.094947e-13 | M82: =M71 -> 9.094947e-13 | N82: =N71 -> 9.094947e-13 | O82: =O71 -> 9.094947e-13
B83: Accounts Receivable | E83: 2501.7 | F83: 2461.9 | G83: 2956.17 | H83: 4025.82 | I83: 4719.67 | J83: 3922.86 | K83: =K182 -> 4899.0448 | L83: =L182 -> 5241.9779 | M83: =M182 -> 5582.7065 | N83: =N182 -> 5917.6689 | O83: =O182 -> 6243.1407
B84: Inventories | E84: 10397.16 | F84: 10864.15 | G84: 11771.16 | H84: 14302.88 | I84: 15836.14 | J84: 18872.65 | K84: =K185 -> 19860.992 | L84: =L185 -> 21251.262 | M84: =M185 -> 22632.594 | N84: =N185 -> 23990.55 | O84: =O185 -> 25310.03
B85: Total Current Assets | F85: =SUM(F82:F84) -> 17980.47 | G85: =SUM(G82:G84) -> 19607.52 | H85: =SUM(H82:H84) -> 18954.59 | I85: =SUM(I82:I84) -> 21175.81 | J85: =SUM(J82:J84) -> 23438.97 | K85: =SUM(K82:K84) -> 24760.037 | L85: =SUM(L82:L84) -> 26493.24 | M85: =SUM(M82:M84) -> 28215.3 | ... O85: =SUM(O82:O84) -> 31553.17
B87: Property Plant & Equipment | F87: 27457.13 | G87: 28854.57 | H87: 27213.52 | I87: 19420.78 | J87: 19854.99 | K87: =K205 -> 21467.603 | L87: =L205 -> 23083.405 | M87: =M205 -> 24686.125 | N87: =N205 -> 26257.343 | O87: =O205 -> 27776.547
B88: Investments | F88: 24841.01 | G88: 29415.02 | H88: 31114.02 | I88: 34719.82 | J88: 38128.43 | K88: =K11*($J$88/$J$11) -> 40988.062 | L88: =L11*($J$88/$J$11) -> 43857.227 | M88: =M11*($J$88/$J$11) -> 46707.946 | N88: =N11*($J$88/$J$11) -> 49510.423 | O88: =O11*($J$88/$J$11) -> 52233.496
B89: Other Assets | F89: 6917.41 | G89: 7953.85 | H89: 14544.03 | I89: 12774.27 | J89: 12369.99 | K89: =$J$89 -> 12369.99 | L89: =$J$89 -> 12369.99 | M89: =$J$89 -> 12369.99 | N89: =$J$89 -> 12369.99 | O89: =$J$89 -> 12369.99
B90: Total Assets | F90: =F85+F87+F88+F89 -> 77196.02 | G90: =G85+G87+G88+G89 -> 85830.96 | H90: =H85+H87+H88+H89 -> 91826.16 | I90: =I85+I87+I88+I89 -> 88090.68 | J90: =J85+J87+J88+J89 -> 93792.38 | K90: =K85+K87+K88+K89 -> 99585.692 | L90: =L85+L87+L88+L89 -> 105803.86 | M90: =M85+M87+M88+M89 -> 111979.36 | ... O90: =O85+O87+O88+O89 -> 123933.2
B93: LIABILITIES
B95: Other Liabilities | E95: 13142.59 | F95: 14491.01 | G95: 16369.66 | H95: 14783.47 | I95: 15019.02 | J95: 15643.52 | K95: =K189 -> 17398.229 | L95: =L189 -> 18616.105 | M95: =M189 -> 19826.152 | N95: =N189 -> 21015.721 | O95: =O189 -> 22171.586
B96: Revolving Credit Line | F96: 0 | G96: 0 | H96: 0 | I96: 0 | J96: 0 | K96: =K282 -> 978.56573 | L96: =L282 -> 2663.1662 | M96: =M282 -> 4092.7217 | N96: =N282 -> 5222.522 | O96: =O282 -> 5999.9989
B97: Total Current Liabilities | F97: =F95+F96 -> 14491.01 | G97: =G95+G96 -> 16369.66 | H97: =H95+H96 -> 14783.47 | I97: =I95+I96 -> 15019.02 | J97: =J95+J96 -> 15643.52 | K97: =K95+K96 -> 18376.795 | L97: =L95+L96 -> 21279.272 | M97: =M95+M96 -> 23918.874 | ... O97: =O95+O96 -> 28171.585
B99: Deferred Taxes | F99: 0 | G99: 0 | H99: 2141.44 | I99: 2582.46 | J99: 3089.62 | K99: =J99+K368 -> 3502.4788 | L99: =K99+L368 -> 3863.1111 | M99: =L99+M368 -> 4175.7099 | N99: =M99+N368 -> 4443.2247 | O99: =N99+O368 -> 4667.505
B100: Long-Term Debt | F100: 249.44 | G100: 306.04 | H100: 11.28 | I100: 91.26 | J100: 2186.22 | K100: =K254 -> 2186.22 | L100: =L254 -> 2186.22 | M100: =M254 -> 2186.22 | N100: =N254 -> 2186.22 | O100: =O254 -> 2186.22
B101: Total Liabilities | F101: =F97+F99+F100 -> 14740.45 | G101: =G97+G99+G100 -> 16675.7 | H101: =H97+H99+H100 -> 16936.19 | I101: =I97+I99+I100 -> 17692.74 | J101: =J97+J99+J100 -> 20919.36 | K101: =K97+K99+K100 -> 24065.494 | L101: =L97+L99+L100 -> 27328.603 | M101: =M97+M99+M100 -> 30280.804 | ... O101: =O97+O99+O100 -> 35025.31
B104: EQUITY
B106: Common Equity | F106: 1232.33 | G106: 1242.8 | H106: 1248.47 | I106: 1251.41 | J106: 1252.95 | K106: =K306 -> 1252.95 | L106: =L306 -> 1252.95 | M106: =M306 -> 1252.95 | N106: =N306 -> 1252.95 | O106: =O306 -> 1252.95
B107: Retained Earnings | F107: 61223.24 | G107: 67912.46 | H107: 73641.5 | I107: 69146.53 | J107: 71620.07 | K107: =K313 -> 74267.248 | L107: =L313 -> 77222.309 | M107: =M313 -> 80445.608 | N107: =N313 -> 83925.336 | O107: =O313 -> 87654.944
B108: Total Shareholders' Equity | F108: =F106+F107 -> 62455.57 | G108: =G106+G107 -> 69155.26 | H108: =H106+H107 -> 74889.97 | I108: =I106+I107 -> 70397.94 | J108: =J106+J107 -> 72873.02 | K108: =K106+K107 -> 75520.198 | L108: =L106+L107 -> 78475.259 | M108: =M106+M107 -> 81698.558 | ... O108: =O106+O107 -> 88907.894
B111: Total Liabilities & Equity | F111: =F101+F108 -> 77196.02 | G111: =G101+G108 -> 85830.96 | H111: =H101+H108 -> 91826.16 | I111: =I101+I108 -> 88090.68 | J111: =J101+J108 -> 93792.38 | K111: =K101+K108 -> 99585.692 | L111: =L101+L108 -> 105803.86 | M111: =M101+M108 -> 111979.36 | ... O111: =O101+O108 -> 123933.2
B114: Check | F114: =ROUND(F90-F111,0) -> 0 | G114: =ROUND(G90-G111,0) -> 0 | H114: =ROUND(H90-H111,0) -> 0 | I114: =ROUND(I90-I111,0) -> 0 | J114: =ROUND(J90-J111,0) -> 0 | K114: =ROUND(K90-K111,0) -> 0 | L114: =ROUND(L90-L111,0) -> 0 | M114: =ROUND(M90-M111,0) -> 0 | ... O114: =ROUND(O90-O111,0) -> 0
A118: 2 | B118: Revenue Schedule
B120: All figures in Rs. Crores unless stated | F120: =F$5 -> 2022 | G120: =G$5 -> 2023 | H120: =H$5 -> 2024 | I120: =I$5 -> 2025 | J120: =J$5 -> 2026 | K120: =K$5 -> 2027E | L120: =L$5 -> 2028E | M120: =M$5 -> 2029E | ... O120: =O$5 -> 2031E
B121: =B$6 -> Model Running: Base Case Drivers
B124: REVENUE
B126: Revenue Growth Rate | G126: =G11/F11-1 -> 0.16942152 | H126: =H11/G11-1 -> 0.041912587 | I126: =I11/H11-1 -> 0.10449588 | J126: =J11/I11-1 -> 0.1017065 | K126: =Inputs!H10 -> 0.075 | L126: =Inputs!I10 -> 0.07 | M126: =Inputs!J10 -> 0.065 | N126: =Inputs!K10 -> 0.06 | O126: =Inputs!L10 -> 0.055
B128: Revenue | F128: =F11 -> 60644.54 | G128: =G11 -> 70919.03 | H128: =H11 -> 73891.43 | I128: =I11 -> 81612.78 | J128: =J11 -> 89913.33 | K128: =$J$11*(K134/100)*(K137/100) -> 96656.83 | L128: =$J$11*(L134/100)*(L137/100) -> 103422.81 | M128: =$J$11*(M134/100)*(M137/100) -> 110145.29 | N128: =$J$11*(N134/100)*(N137/100) -> 116754.01 | O128: =$J$11*(O134/100)*(O137/100) -> 123175.48
B131: VOLUME & PRICE DECOMPOSITION (Illustrative — FY27E-FY31E only)
B133: Illustrative Volume Growth % | K133: =Inputs!H70 -> 0.045 | L133: =Inputs!I70 -> 0.0425 | M133: =Inputs!J70 -> 0.04 | N133: =Inputs!K70 -> 0.0375 | O133: =Inputs!L70 -> 0.035
B134: Volume Index (FY26A = 100) | J134: 100 | K134: =J134*(1+K133) -> 104.5 | L134: =K134*(1+L133) -> 108.94125 | M134: =L134*(1+M133) -> 113.2989 | N134: =M134*(1+N133) -> 117.54761 | O134: =N134*(1+O133) -> 121.66178
B136: Realization / Price Growth % (Residual) | K136: =(1+K126)/(1+K133)-1 -> 0.028708134 | L136: =(1+L126)/(1+L133)-1 -> 0.026378897 | M136: =(1+M126)/(1+M133)-1 -> 0.024038462 | N136: =(1+N126)/(1+N133)-1 -> 0.021686747 | O136: =(1+O126)/(1+O133)-1 -> 0.019323671
B137: Realization / Price Index (FY26A = 100) | J137: 100 | K137: =J137*(1+K136) -> 102.87081 | L137: =K137*(1+L136) -> 105.58443 | M137: =L137*(1+M136) -> 108.12252 | N137: =M137*(1+N136) -> 110.46735 | O137: =N137*(1+O136) -> 112.60198
B139: Memo: Revenue = Volume Index x Price Index (both indexed to 100 at FY26A); volume split is illustrative and mathematically nets out so consolidated Revenue is unchanged from the driver-based figure.
A142: 2 | B142: Cost Schedule
B144: All figures in Rs. Crores unless stated | F144: =F$5 -> 2022 | G144: =G$5 -> 2023 | H144: =H$5 -> 2024 | I144: =I$5 -> 2025 | J144: =J$5 -> 2026 | K144: =K$5 -> 2027E | L144: =L$5 -> 2028E | M144: =M$5 -> 2029E | ... O144: =O$5 -> 2031E
B145: =B$6 -> Model Running: Base Case Drivers
B148: EBITDA MARGIN
B150: EBITDA Margin % | F150: =F18/F11 -> 0.31744243 | G150: =G18/G11 -> 0.35233251 | H150: =H18/H11 -> 0.34171473 | I150: =I18/I11 -> 0.31831056 | J150: =J18/J11 -> 0.30382492 | K150: =Inputs!H17 -> 0.295 | L150: =Inputs!I17 -> 0.31 | M150: =Inputs!J17 -> 0.32 | N150: =Inputs!K17 -> 0.328 | O150: =Inputs!L17 -> 0.335
B153: COST BUILD (Projection Period)
B155: Total Opex = Revenue x (1 - EBITDA Margin) | K155: =K128*(1-K150) -> 68143.065 | L155: =L128*(1-L150) -> 71361.737 | M155: =M128*(1-M150) -> 74898.797 | N155: =N128*(1-N150) -> 78458.693 | O155: =O128*(1-O150) -> 81911.693
B157: COGS % of Total Opex | K157: 0.687 | L157: 0.687 | M157: 0.687 | N157: 0.687 | O157: 0.687
B158: SG&A % of Total Opex | K158: 0.111 | L158: 0.111 | M158: 0.111 | N158: 0.111 | O158: 0.111
B159: Other Opex % of Total Opex | K159: 0.202 | L159: 0.202 | M159: 0.202 | N159: 0.202 | O159: 0.202
B161: COGS | K161: =K155*K157 -> 46814.286 | L161: =L155*L157 -> 49025.514 | M161: =M155*M157 -> 51455.474 | N161: =N155*N157 -> 53901.122 | O161: =O155*O157 -> 56273.333
B162: SG&A | K162: =K155*K158 -> 7563.8802 | L162: =L155*L158 -> 7921.1529 | M162: =M155*M158 -> 8313.7665 | N162: =N155*N158 -> 8708.9149 | O162: =O155*O158 -> 9092.1979
B163: Other Opex | K163: =K155*K159 -> 13764.899 | L163: =L155*L159 -> 14415.071 | M163: =M155*M159 -> 15129.557 | N163: =N155*N159 -> 15848.656 | O163: =O155*O159 -> 16546.162
B166: MEMO: ILLUSTRATIVE PER-UNIT COST DECOMPOSITION (Volume Basis, FY27E-FY31E)
B168: Variable Cost per Volume-Unit (Illustrative) | K168: =K161/K134*100 -> 44798.359 | L168: =L161/L134*100 -> 45001.791 | M168: =M161/M134*100 -> 45415.687 | N168: =N161/N134*100 -> 45854.716 | O168: =O161/O134*100 -> 46253.914
B169: Fixed Cost: SG&A + Other Opex (Illustrative) | K169: =K162+K163 -> 21328.779 | L169: =L162+L163 -> 22336.224 | M169: =M162+M163 -> 23443.324 | N169: =N162+N163 -> 24557.571 | O169: =O162+O163 -> 25638.36
A173: 2 | B173: Working Capital Schedule
B175: All figures in Rs. Crores unless stated | F175: =F$5 -> 2022 | G175: =G$5 -> 2023 | H175: =H$5 -> 2024 | I175: =I$5 -> 2025 | J175: =J$5 -> 2026 | K175: =K$5 -> 2027E | L175: =L$5 -> 2028E | M175: =M$5 -> 2029E | ... O175: =O$5 -> 2031E
B176: =B$6 -> Model Running: Base Case Drivers
...
